{
  "ExportMetadata": {
    "ExportTimestamp": "2026-02-10T11:58:29.345Z",
    "SearchQuery": "t:Texture2D",
    "ProvidersUsed": [
      "asset"
    ],
    "ResultCount": 204,
    "ExportFormat": "JSON"
  },
  "Results": [
    {
      "Id": "GlobalObjectId_V1-1-2289f8e404d1d0847acddc5415b67eff-2800000-0",
      "Label": "",
      "Description": "",
      "Provider": "asset",
      "Type": "Asset",
      "Path": "Assets/Model/10eb4f3be7b1.jpg",
      "Thumbnail": "",
      "Score": 49.0,
      "Tags": [
        "asset"
      ],
      "FileSize": 0,
      "LastModified": "",
      "IsSelectable": true,
      "Properties": {}
    },
    {
      "Id": "GlobalObjectId_V1-1-4db9d60b37569954da8b34f55b5001b0-2800000-0",
      "Label": "",
      "Description": "",
      "Provider": "asset",
      "Type": "Asset",
      "Path": "Assets/Model/Dallas_City/Textures/Dallas-Part_4.jpg",
      "Thumbnail": "",
      "Score": 68.0,
      "Tags": [
        "asset"
      ],
      "FileSize": 0,
      "LastModified": "",
      "IsSelectable": true,
      "Properties": {}
    },
    {
      "Id": "GlobalObjectId_V1-1-a8101ca79c1202349924f1041c53fc85-2800000-0",
      "Label": "",
      "Description": "",
      "Provider": "asset",
      "Type": "Asset",
      "Path": "Assets/Model/Dallas_City/Textures/Dallas-Part_3.jpg",
      "Thumbnail": "",
      "Score": 68.0,
      "Tags": [
        "asset"
      ],
      "FileSize": 0,
      "LastModified": "",
      "IsSelectable": true,
      "Properties": {}
    },
    {
      "Id": "GlobalObjectId_V1-1-b215b91f7f8656c4aa074dff43bc1e2c-2800000-0",
      "Label": "",
      "Description": "",
      "Provider": "asset",
      "Type": "Asset",
      "Path": "Assets/Model/Dallas_City/Textures/Dallas-Part_6.jpg",
      "Thumbnail": "",
      "Score": 68.0,
      "Tags": [
        "asset"
      ],
      "FileSize": 0,
      "LastModified": "",
      "IsSelectable": true,
      "Properties": {}
    },
    {
      "Id": "GlobalObjectId_V1-1-b5cd3853658b43c4d93c00ceb2f504ad-2800000-0",
      "Label": "",
      "Description": "",
      "Provider": "asset",
      "Type": "Asset",
      "Path": "Assets/Model/Dallas_City/Textures/Dallas-Part_2.jpg",
      "Thumbnail": "",
      "Score": 68.0,
      "Tags": [
        "asset"
      ],
      "FileSize": 0,
      "LastModified": "",
      "IsSelectable": true,
      "Properties": {}
    },
    {
      "Id": "GlobalObjectId_V1-1-bd568e99fc48e184c9d9a686a42b2857-2800000-0",
      "Label": "",
      "Description": "",
      "Provider": "asset",
      "Type": "Asset",
      "Path": "Assets/Model/Dallas_City/Textures/Dallas-Part_1.png",
      "Thumbnail": "",
      "Score": 68.0,
      "Tags": [
        "asset"
      ],
      "FileSize": 0,
      "LastModified": "",
      "IsSelectable": true,
      "Properties": {}
    },
    {
      "Id": "GlobalObjectId_V1-1-c2abbe1cd919cff42bc7ecafde735dd2-2800000-0",
      "Label": "",
      "Description": "",
      "Provider": "asset",
      "Type": "Asset",
      "Path": "Assets/Model/Dallas_City/Textures/Dallas-Part_5.jpg",
      "Thumbnail": "",
      "Score": 68.0,
      "Tags": [
        "asset"
      ],
      "FileSize": 0,
      "LastModified": "",
      "IsSelectable": true,
      "Properties": {}
    },
    {
      "Id": "GlobalObjectId_V1-1-dffef66376be4fa480fb02b19edbe903-2800000-0",
      "Label": "",
      "Description": "",
      "Provider": "asset",
      "Type": "Asset",
      "Path": "Assets/TextMesh Pro/Sprites/EmojiOne.png",
      "Thumbnail": "",
      "Score": 69.0,
      "Tags": [
        "asset"
      ],
      "FileSize": 0,
      "LastModified": "",
      "IsSelectable": true,
      "Properties": {}
    },
    {
      "Id": "GlobalObjectId_V1-1-0c2b555ca30b2444b85699fbfc13c2d7-2800000-0",
      "Label": "",
      "Description": "",
      "Provider": "asset",
      "Type": "Asset",
      "Path": "Assets/texture/Gemini_Generated_Image_w9a96fw9a96fw9a9.png",
      "Thumbnail": "",
      "Score": 71.0,
      "Tags": [
        "asset"
      ],
      "FileSize": 0,
      "LastModified": "",
      "IsSelectable": true,
      "Properties": {}
    },
    {
      "Id": "GlobalObjectId_V1-1-34f46461b24865c4fbbad380688aa97d-2800000-0",
      "Label": "",
      "Description": "",
      "Provider": "asset",
      "Type": "Asset",
      "Path": "Assets/Model/TextureHorro/Gemini_Generated_Image_qz09sbqz09sbqz09 1.png",
      "Thumbnail": "",
      "Score": 71.0,
      "Tags": [
        "asset"
      ],
      "FileSize": 0,
      "LastModified": "",
      "IsSelectable": true,
      "Properties": {}
    },
    {
      "Id": "GlobalObjectId_V1-1-3c5731be80713ee4dbf5ecc9a07ff823-2800000-0",
      "Label": "",
      "Description": "",
      "Provider": "asset",
      "Type": "Asset",
      "Path": "Assets/Model/TextureHorro/Gemini_Generated_Image_et6gudet6gudet6g 1.png",
      "Thumbnail": "",
      "Score": 71.0,
      "Tags": [
        "asset"
      ],
      "FileSize": 0,
      "LastModified": "",
      "IsSelectable": true,
      "Properties": {}
    },
    {
      "Id": "GlobalObjectId_V1-1-3ef1697f698530c4889d215f0c55449a-2800000-0",
      "Label": "",
      "Description": "",
      "Provider": "asset",
      "Type": "Asset",
      "Path": "Assets/Model/TextureHorro/Gemini_Generated_Image_c4x42ic4x42ic4x4 1.png",
      "Thumbnail": "",
      "Score": 71.0,
      "Tags": [
        "asset"
      ],
      "FileSize": 0,
      "LastModified": "",
      "IsSelectable": true,
      "Properties": {}
    },
    {
      "Id": "GlobalObjectId_V1-1-40d65bbcd1cc30246b365375de844949-2800000-0",
      "Label": "",
      "Description": "",
      "Provider": "asset",
      "Type": "Asset",
      "Path": "Assets/texture/Gemini_Generated_Image_x6ri5zx6ri5zx6ri (1) (1).png",
      "Thumbnail": "",
      "Score": 71.0,
      "Tags": [
        "asset"
      ],
      "FileSize": 0,
      "LastModified": "",
      "IsSelectable": true,
      "Properties": {}
    },
    {
      "Id": "GlobalObjectId_V1-1-5f905ab08f8262d48922249e82316a0c-2800000-0",
      "Label": "",
      "Description": "",
      "Provider": "asset",
      "Type": "Asset",
      "Path": "Assets/Model/TextureHorro/Gemini_Generated_Image_nsrjksnsrjksnsrj 1.png",
      "Thumbnail": "",
      "Score": 71.0,
      "Tags": [
        "asset"
      ],
      "FileSize": 0,
      "LastModified": "",
      "IsSelectable": true,
      "Properties": {}
    },
    {
      "Id": "GlobalObjectId_V1-1-638e24cb0a19f644dac840ec1b12c71b-2800000-0",
      "Label": "",
      "Description": "",
      "Provider": "asset",
      "Type": "Asset",
      "Path": "Assets/Model/TextureHorro/Gemini_Generated_Image_qj1yuwqj1yuwqj1y 1.png",
      "Thumbnail": "",
      "Score": 71.0,
      "Tags": [
        "asset"
      ],
      "FileSize": 0,
      "LastModified": "",
      "IsSelectable": true,
      "Properties": {}
    },
    {
      "Id": "GlobalObjectId_V1-1-6af75b3336fab6d48baf05a4824e8fcf-2800000-0",
      "Label": "",
      "Description": "",
      "Provider": "asset",
      "Type": "Asset",
      "Path": "Assets/Model/TextureHorro/Gemini_Generated_Image_hn5ytfhn5ytfhn5y.png",
      "Thumbnail": "",
      "Score": 71.0,
      "Tags": [
        "asset"
      ],
      "FileSize": 0,
      "LastModified": "",
      "IsSelectable": true,
      "Properties": {}
    },
    {
      "Id": "GlobalObjectId_V1-1-71ca340f1919b034ca698abdb0d4ff84-2800000-0",
      "Label": "",
      "Description": "",
      "Provider": "asset",
      "Type": "Asset",
      "Path": "Assets/Model/TextureHorro/Gemini_Generated_Image_qj1yuwqj1yuwqj1y.png",
      "Thumbnail": "",
      "Score": 71.0,
      "Tags": [
        "asset"
      ],
      "FileSize": 0,
      "LastModified": "",
      "IsSelectable": true,
      "Properties": {}
    },
    {
      "Id": "GlobalObjectId_V1-1-810769342aa6eb0469a6424b4fb17f10-2800000-0",
      "Label": "",
      "Description": "",
      "Provider": "asset",
      "Type": "Asset",
      "Path": "Assets/Model/Gemini_Generated_Image_hziubdhziubdhziu.png",
      "Thumbnail": "",
      "Score": 71.0,
      "Tags": [
        "asset"
      ],
      "FileSize": 0,
      "LastModified": "",
      "IsSelectable": true,
      "Properties": {}
    },
    {
      "Id": "GlobalObjectId_V1-1-8f1eaa42b9cf30f408ecb36178a0b733-2800000-0",
      "Label": "",
      "Description": "",
      "Provider": "asset",
      "Type": "Asset",
      "Path": "Assets/Model/Gemini_Generated_Image_lpg849lpg849lpg8.png",
      "Thumbnail": "",
      "Score": 71.0,
      "Tags": [
        "asset"
      ],
      "FileSize": 0,
      "LastModified": "",
      "IsSelectable": true,
      "Properties": {}
    },
    {
      "Id": "GlobalObjectId_V1-1-96d71bd568cdb4945b241c27a1a97d34-2800000-0",
      "Label": "",
      "Description": "",
      "Provider": "asset",
      "Type": "Asset",
      "Path": "Assets/Model/TextureHorro/Gemini_Generated_Image_nsrjksnsrjksnsrj.png",
      "Thumbnail": "",
      "Score": 71.0,
      "Tags": [
        "asset"
      ],
      "FileSize": 0,
      "LastModified": "",
      "IsSelectable": true,
      "Properties": {}
    },
    {
      "Id": "GlobalObjectId_V1-1-b414f4a8e1c7f2a4cafba4eae8b6dd2f-2800000-0",
      "Label": "",
      "Description": "",
      "Provider": "asset",
      "Type": "Asset",
      "Path": "Assets/Model/TextureHorro/Gemini_Generated_Image_3twrnj3twrnj3twr 1.png",
      "Thumbnail": "",
      "Score": 71.0,
      "Tags": [
        "asset"
      ],
      "FileSize": 0,
      "LastModified": "",
      "IsSelectable": true,
      "Properties": {}
    },
    {
      "Id": "GlobalObjectId_V1-1-c9132ab21aeb9f54fa86cedccc8899f8-2800000-0",
      "Label": "",
      "Description": "",
      "Provider": "asset",
      "Type": "Asset",
      "Path": "Assets/Model/TextureHorro/Gemini_Generated_Image_qz09sbqz09sbqz09.png",
      "Thumbnail": "",
      "Score": 71.0,
      "Tags": [
        "asset"
      ],
      "FileSize": 0,
      "LastModified": "",
      "IsSelectable": true,
      "Properties": {}
    },
    {
      "Id": "GlobalObjectId_V1-1-d0f29a8d3187bcc4ea8f652f92cb2cb4-2800000-0",
      "Label": "",
      "Description": "",
      "Provider": "asset",
      "Type": "Asset",
      "Path": "Assets/texture/Gemini_Generated_Image_h19thjh19thjh19t (1).png",
      "Thumbnail": "",
      "Score": 71.0,
      "Tags": [
        "asset"
      ],
      "FileSize": 0,
      "LastModified": "",
      "IsSelectable": true,
      "Properties": {}
    },
    {
      "Id": "GlobalObjectId_V1-1-d30f4752d69f1454c9053c32ac52ecf1-2800000-0",
      "Label": "",
      "Description": "",
      "Provider": "asset",
      "Type": "Asset",
      "Path": "Assets/Model/TextureHorro/Gemini_Generated_Image_c4x42ic4x42ic4x4.png",
      "Thumbnail": "",
      "Score": 71.0,
      "Tags": [
        "asset"
      ],
      "FileSize": 0,
      "LastModified": "",
      "IsSelectable": true,
      "Properties": {}
    },
    {
      "Id": "GlobalObjectId_V1-1-dc2744d366a71c34ca7cd71e41e7acf1-2800000-0",
      "Label": "",
      "Description": "",
      "Provider": "asset",
      "Type": "Asset",
      "Path": "Assets/Model/TextureHorro/Gemini_Generated_Image_3twrnj3twrnj3twr.png",
      "Thumbnail": "",
      "Score": 71.0,
      "Tags": [
        "asset"
      ],
      "FileSize": 0,
      "LastModified": "",
      "IsSelectable": true,
      "Properties": {}
    },
    {
      "Id": "GlobalObjectId_V1-1-e3d3f79c6f592a844a7627e5f1e72eb9-2800000-0",
      "Label": "",
      "Description": "",
      "Provider": "asset",
      "Type": "Asset",
      "Path": "Assets/Model/TextureHorro/Gemini_Generated_Image_erh1veerh1veerh1 1.png",
      "Thumbnail": "",
      "Score": 71.0,
      "Tags": [
        "asset"
      ],
      "FileSize": 0,
      "LastModified": "",
      "IsSelectable": true,
      "Properties": {}
    },
    {
      "Id": "GlobalObjectId_V1-1-e4a383655b10d0743a09afe34d2b8ce4-2800000-0",
      "Label": "",
      "Description": "",
      "Provider": "asset",
      "Type": "Asset",
      "Path": "Assets/Model/TextureHorro/Gemini_Generated_Image_erh1veerh1veerh1.png",
      "Thumbnail": "",
      "Score": 71.0,
      "Tags": [
        "asset"
      ],
      "FileSize": 0,
      "LastModified": "",
      "IsSelectable": true,
      "Properties": {}
    },
    {
      "Id": "GlobalObjectId_V1-1-eaac18cde5a0a6e469a42ad162f06cda-2800000-0",
      "Label": "",
      "Description": "",
      "Provider": "asset",
      "Type": "Asset",
      "Path": "Assets/Model/TextureHorro/Gemini_Generated_Image_et6gudet6gudet6g.png",
      "Thumbnail": "",
      "Score": 71.0,
      "Tags": [
        "asset"
      ],
      "FileSize": 0,
      "LastModified": "",
      "IsSelectable": true,
      "Properties": {}
    },
    {
      "Id": "GlobalObjectId_V1-1-ed9a860f741a1264eb8fa8af87cb3311-2800000-0",
      "Label": "",
      "Description": "",
      "Provider": "asset",
      "Type": "Asset",
      "Path": "Assets/Model/TextureHorro/Gemini_Generated_Image_hknihghknihghkni.png",
      "Thumbnail": "",
      "Score": 71.0,
      "Tags": [
        "asset"
      ],
      "FileSize": 0,
      "LastModified": "",
      "IsSelectable": true,
      "Properties": {}
    },
    {
      "Id": "GlobalObjectId_V1-1-f88792692ca4dd847a6ca24e2b1ab6cd-2800000-0",
      "Label": "",
      "Description": "",
      "Provider": "asset",
      "Type": "Asset",
      "Path": "Assets/Model/TextureHorro/Gemini_Generated_Image_hn5ytfhn5ytfhn5y 1.png",
      "Thumbnail": "",
      "Score": 71.0,
      "Tags": [
        "asset"
      ],
      "FileSize": 0,
      "LastModified": "",
      "IsSelectable": true,
      "Properties": {}
    },
    {
      "Id": "GlobalObjectId_V1-1-e3265ab4bf004d28a9537516768c1c75-2800000-0",
      "Label": "",
      "Description": "",
      "Provider": "asset",
      "Type": "Asset",
      "Path": "Assets/TextMesh Pro/Fonts/LiberationSans.ttf",
      "Thumbnail": "",
      "Score": 76.0,
      "Tags": [
        "asset"
      ],
      "FileSize": 0,
      "LastModified": "",
      "IsSelectable": true,
      "Properties": {}
    },
    {
      "Id": "GlobalObjectId_V1-3-2e498d1c8094910479dc3e1b768306a4-28268798066460806-0",
      "Label": "",
      "Description": "",
      "Provider": "asset",
      "Type": "Asset",
      "Path": "Assets/TextMesh Pro/Resources/Fonts & Materials/LiberationSans SDF - Fallback.asset",
      "Thumbnail": "",
      "Score": 76.0,
      "Tags": [
        "asset"
      ],
      "FileSize": 0,
      "LastModified": "",
      "IsSelectable": true,
      "Properties": {}
    },
    {
      "Id": "GlobalObjectId_V1-3-8f586378b4e144a9851e7b34d9b748ee-28684132378477856-0",
      "Label": "",
      "Description": "",
      "Provider": "asset",
      "Type": "Asset",
      "Path": "Assets/TextMesh Pro/Resources/Fonts & Materials/LiberationSans SDF.asset",
      "Thumbnail": "",
      "Score": 76.0,
      "Tags": [
        "asset"
      ],
      "FileSize": 0,
      "LastModified": "",
      "IsSelectable": true,
      "Properties": {}
    },
    {
      "Id": "GlobalObjectId_V1-1-36e502734eef249458075cef8d83633e-2800000-0",
      "Label": "",
      "Description": "",
      "Provider": "asset",
      "Type": "Asset",
      "Path": "Assets/Particlecollection_Free samples/Texture/Sprays_01.png",
      "Thumbnail": "",
      "Score": 83.0,
      "Tags": [
        "asset"
      ],
      "FileSize": 0,
      "LastModified": "",
      "IsSelectable": true,
      "Properties": {}
    },
    {
      "Id": "GlobalObjectId_V1-1-57bcc2f18d7d7ca46b806ff2e7ddee2e-2800000-0",
      "Label": "",
      "Description": "",
      "Provider": "asset",
      "Type": "Asset",
      "Path": "Assets/Model/T_ClawHammer_01_Normal.tga",
      "Thumbnail": "",
      "Score": 84.0,
      "Tags": [
        "asset"
      ],
      "FileSize": 0,
      "LastModified": "",
      "IsSelectable": true,
      "Properties": {}
    },
    {
      "Id": "GlobalObjectId_V1-1-6d21618d2e4a81d4dab239302fa9131d-2800000-0",
      "Label": "",
      "Description": "",
      "Provider": "asset",
      "Type": "Asset",
      "Path": "Assets/Model/T_ClawHammer_01_Albedo.tga",
      "Thumbnail": "",
      "Score": 84.0,
      "Tags": [
        "asset"
      ],
      "FileSize": 0,
      "LastModified": "",
      "IsSelectable": true,
      "Properties": {}
    },
    {
      "Id": "GlobalObjectId_V1-1-48ef1efab58ce7445abd9c41b56f05f7-2800000-0",
      "Label": "",
      "Description": "",
      "Provider": "asset",
      "Type": "Asset",
      "Path": "Assets/Particlecollection_Free samples/Texture/airflow_02.png",
      "Thumbnail": "",
      "Score": 97.0,
      "Tags": [
        "asset"
      ],
      "FileSize": 0,
      "LastModified": "",
      "IsSelectable": true,
      "Properties": {}
    },
    {
      "Id": "GlobalObjectId_V1-1-69b766b60bb267743a5790643a6cc02a-2800000-0",
      "Label": "",
      "Description": "",
      "Provider": "asset",
      "Type": "Asset",
      "Path": "Assets/Particlecollection_Free samples/Texture/arrow_01.png",
      "Thumbnail": "",
      "Score": 97.0,
      "Tags": [
        "asset"
      ],
      "FileSize": 0,
      "LastModified": "",
      "IsSelectable": true,
      "Properties": {}
    },
    {
      "Id": "GlobalObjectId_V1-1-b33d68e8275874d4ea316190b470b988-2800000-0",
      "Label": "",
      "Description": "",
      "Provider": "asset",
      "Type": "Asset",
      "Path": "Assets/Particlecollection_Free samples/Texture/airflow_01.png",
      "Thumbnail": "",
      "Score": 97.0,
      "Tags": [
        "asset"
      ],
      "FileSize": 0,
      "LastModified": "",
      "IsSelectable": true,
      "Properties": {}
    },
    {
      "Id": "GlobalObjectId_V1-1-df67d36ca3f3dcf44aabb931cc89370d-2800000-0",
      "Label": "",
      "Description": "",
      "Provider": "asset",
      "Type": "Asset",
      "Path": "Assets/Particlecollection_Free samples/Texture/airflow_03.png",
      "Thumbnail": "",
      "Score": 97.0,
      "Tags": [
        "asset"
      ],
      "FileSize": 0,
      "LastModified": "",
      "IsSelectable": true,
      "Properties": {}
    },
    {
      "Id": "GlobalObjectId_V1-1-492a9e2910c8dc948983e2e7bcd06bb4-2800000-0",
      "Label": "",
      "Description": "",
      "Provider": "asset",
      "Type": "Asset",
      "Path": "Assets/Model/c3b2fdf4355b.jpg",
      "Thumbnail": "",
      "Score": 99.0,
      "Tags": [
        "asset"
      ],
      "FileSize": 0,
      "LastModified": "",
      "IsSelectable": true,
      "Properties": {}
    },
    {
      "Id": "GlobalObjectId_V1-1-2b08b7b8e155e02479bb0f538d09bb6e-2800000-0",
      "Label": "",
      "Description": "",
      "Provider": "asset",
      "Type": "Asset",
      "Path": "Assets/Model/TEXTURES/glock_4K_Roughness.png",
      "Thumbnail": "",
      "Score": 103.0,
      "Tags": [
        "asset"
      ],
      "FileSize": 0,
      "LastModified": "",
      "IsSelectable": true,
      "Properties": {}
    },
    {
      "Id": "GlobalObjectId_V1-1-2d38b44789715cd4383414c0d8f25e41-2800000-0",
      "Label": "",
      "Description": "",
      "Provider": "asset",
      "Type": "Asset",
      "Path": "Assets/Particlecollection_Free samples/Texture/ground_no.png",
      "Thumbnail": "",
      "Score": 103.0,
      "Tags": [
        "asset"
      ],
      "FileSize": 0,
      "LastModified": "",
      "IsSelectable": true,
      "Properties": {}
    },
    {
      "Id": "GlobalObjectId_V1-1-9915b8dd43b967348baaf8b42905cf1d-2800000-0",
      "Label": "",
      "Description": "",
      "Provider": "asset",
      "Type": "Asset",
      "Path": "Assets/Model/TEXTURES/glock_4K_BaseColor.png",
      "Thumbnail": "",
      "Score": 103.0,
      "Tags": [
        "asset"
      ],
      "FileSize": 0,
      "LastModified": "",
      "IsSelectable": true,
      "Properties": {}
    },
    {
      "Id": "GlobalObjectId_V1-1-e3027c8be41eb364d933c5a82c7bde0d-2800000-0",
      "Label": "",
      "Description": "",
      "Provider": "asset",
      "Type": "Asset",
      "Path": "Assets/Particlecollection_Free samples/Texture/ground.png",
      "Thumbnail": "",
      "Score": 103.0,
      "Tags": [
        "asset"
      ],
      "FileSize": 0,
      "LastModified": "",
      "IsSelectable": true,
      "Properties": {}
    },
    {
      "Id": "GlobalObjectId_V1-1-f61018cb4f619c24db26650d0f28612c-2800000-0",
      "Label": "",
      "Description": "",
      "Provider": "asset",
      "Type": "Asset",
      "Path": "Assets/Model/TEXTURES/glock_4K_Metallic.png",
      "Thumbnail": "",
      "Score": 103.0,
      "Tags": [
        "asset"
      ],
      "FileSize": 0,
      "LastModified": "",
      "IsSelectable": true,
      "Properties": {}
    },
    {
      "Id": "GlobalObjectId_V1-1-fa40acfb1a9511742ad7800eaa63a42a-2800000-0",
      "Label": "",
      "Description": "",
      "Provider": "asset",
      "Type": "Asset",
      "Path": "Assets/Model/TEXTURES/glock_4K_Normal.png",
      "Thumbnail": "",
      "Score": 103.0,
      "Tags": [
        "asset"
      ],
      "FileSize": 0,
      "LastModified": "",
      "IsSelectable": true,
      "Properties": {}
    },
    {
      "Id": "GlobalObjectId_V1-1-062e4cda4e285ed4a91e994428a1dc2d-2800000-0",
      "Label": "",
      "Description": "",
      "Provider": "asset",
      "Type": "Asset",
      "Path": "Assets/Particlecollection_Free samples/Texture/hit_03.png",
      "Thumbnail": "",
      "Score": 104.0,
      "Tags": [
        "asset"
      ],
      "FileSize": 0,
      "LastModified": "",
      "IsSelectable": true,
      "Properties": {}
    },
    {
      "Id": "GlobalObjectId_V1-1-9ab0b862f3010da43a75dabe2ad5ce02-2800000-0",
      "Label": "",
      "Description": "",
      "Provider": "asset",
      "Type": "Asset",
      "Path": "Assets/Particlecollection_Free samples/Texture/hit_01.png",
      "Thumbnail": "",
      "Score": 104.0,
      "Tags": [
        "asset"
      ],
      "FileSize": 0,
      "LastModified": "",
      "IsSelectable": true,
      "Properties": {}
    },
    {
      "Id": "GlobalObjectId_V1-1-b20ede1b23768e44db15cb8c7c15e130-2800000-0",
      "Label": "",
      "Description": "",
      "Provider": "asset",
      "Type": "Asset",
      "Path": "Assets/Particlecollection_Free samples/Texture/hit_02.png",
      "Thumbnail": "",
      "Score": 104.0,
      "Tags": [
        "asset"
      ],
      "FileSize": 0,
      "LastModified": "",
      "IsSelectable": true,
      "Properties": {}
    },
    {
      "Id": "GlobalObjectId_V1-1-07bc55e40a51311439ec10a387f4d877-2800000-0",
      "Label": "",
      "Description": "",
      "Provider": "asset",
      "Type": "Asset",
      "Path": "Assets/SU3DJPFont/Fonts/MPlusTestflight63a/mplus-1mn-light.ttf",
      "Thumbnail": "",
      "Score": 109.0,
      "Tags": [
        "asset"
      ],
      "FileSize": 0,
      "LastModified": "",
      "IsSelectable": true,
      "Properties": {}
    },
    {
      "Id": "GlobalObjectId_V1-1-0bf4dd404c55e6a498cb2b9fc87a7d96-2800000-0",
      "Label": "",
      "Description": "",
      "Provider": "asset",
      "Type": "Asset",
      "Path": "Assets/SU3DJPFont/Fonts/MPlusTestflight63a/mplus-2c-light.ttf",
      "Thumbnail": "",
      "Score": 109.0,
      "Tags": [
        "asset"
      ],
      "FileSize": 0,
      "LastModified": "",
      "IsSelectable": true,
      "Properties": {}
    },
    {
      "Id": "GlobalObjectId_V1-1-0d43dcac5e496144e868c7df425fb374-2800000-0",
      "Label": "",
      "Description": "",
      "Provider": "asset",
      "Type": "Asset",
      "Path": "Assets/SU3DJPFont/Fonts/MPlusTestflight63a/mplus-1mn-thin.ttf",
      "Thumbnail": "",
      "Score": 109.0,
      "Tags": [
        "asset"
      ],
      "FileSize": 0,
      "LastModified": "",
      "IsSelectable": true,
      "Properties": {}
    },
    {
      "Id": "GlobalObjectId_V1-1-1aed92eefee870545a2d5e19bfa51307-2800000-0",
      "Label": "",
      "Description": "",
      "Provider": "asset",
      "Type": "Asset",
      "Path": "Assets/SU3DJPFont/Fonts/MPlusTestflight63a/mplus-2m-bold.ttf",
      "Thumbnail": "",
      "Score": 109.0,
      "Tags": [
        "asset"
      ],
      "FileSize": 0,
      "LastModified": "",
      "IsSelectable": true,
      "Properties": {}
    },
    {
      "Id": "GlobalObjectId_V1-1-26b84f9316527c0498207087e1eafde2-2800000-0",
      "Label": "",
      "Description": "",
      "Provider": "asset",
      "Type": "Asset",
      "Path": "Assets/SU3DJPFont/Fonts/MPlusTestflight63a/mplus-2c-heavy.ttf",
      "Thumbnail": "",
      "Score": 109.0,
      "Tags": [
        "asset"
      ],
      "FileSize": 0,
      "LastModified": "",
      "IsSelectable": true,
      "Properties": {}
    },
    {
      "Id": "GlobalObjectId_V1-1-33ba5080df195034aa054c58e86cf5f5-2800000-0",
      "Label": "",
      "Description": "",
      "Provider": "asset",
      "Type": "Asset",
      "Path": "Assets/SU3DJPFont/Fonts/MPlusTestflight63a/mplus-2p-medium.ttf",
      "Thumbnail": "",
      "Score": 109.0,
      "Tags": [
        "asset"
      ],
      "FileSize": 0,
      "LastModified": "",
      "IsSelectable": true,
      "Properties": {}
    },
    {
      "Id": "GlobalObjectId_V1-1-381a3c75237c7a5488e9298f51a282a1-2800000-0",
      "Label": "",
      "Description": "",
      "Provider": "asset",
      "Type": "Asset",
      "Path": "Assets/SU3DJPFont/Fonts/MPlusTestflight63a/mplus-2m-light.ttf",
      "Thumbnail": "",
      "Score": 109.0,
      "Tags": [
        "asset"
      ],
      "FileSize": 0,
      "LastModified": "",
      "IsSelectable": true,
      "Properties": {}
    },
    {
      "Id": "GlobalObjectId_V1-1-49c6f13e1689b5246aec6c7a3a1e2240-2800000-0",
      "Label": "",
      "Description": "",
      "Provider": "asset",
      "Type": "Asset",
      "Path": "Assets/SU3DJPFont/Fonts/MPlusTestflight63a/mplus-2m-thin.ttf",
      "Thumbnail": "",
      "Score": 109.0,
      "Tags": [
        "asset"
      ],
      "FileSize": 0,
      "LastModified": "",
      "IsSelectable": true,
      "Properties": {}
    },
    {
      "Id": "GlobalObjectId_V1-1-4c387066fd2bd6047a0508c3d7ea86b6-2800000-0",
      "Label": "",
      "Description": "",
      "Provider": "asset",
      "Type": "Asset",
      "Path": "Assets/SU3DJPFont/Fonts/MPlusTestflight63a/mplus-1c-bold.ttf",
      "Thumbnail": "",
      "Score": 109.0,
      "Tags": [
        "asset"
      ],
      "FileSize": 0,
      "LastModified": "",
      "IsSelectable": true,
      "Properties": {}
    },
    {
      "Id": "GlobalObjectId_V1-1-4f1f90e5319c1b647a883bd5191b6ff9-2800000-0",
      "Label": "",
      "Description": "",
      "Provider": "asset",
      "Type": "Asset",
      "Path": "Assets/SU3DJPFont/Fonts/MPlusTestflight63a/mplus-1p-thin.ttf",
      "Thumbnail": "",
      "Score": 109.0,
      "Tags": [
        "asset"
      ],
      "FileSize": 0,
      "LastModified": "",
      "IsSelectable": true,
      "Properties": {}
    },
    {
      "Id": "GlobalObjectId_V1-1-52c557479f6adb642b45060b3b5c7c16-2800000-0",
      "Label": "",
      "Description": "",
      "Provider": "asset",
      "Type": "Asset",
      "Path": "Assets/SU3DJPFont/Fonts/MPlusTestflight63a/mplus-2m-regular.ttf",
      "Thumbnail": "",
      "Score": 109.0,
      "Tags": [
        "asset"
      ],
      "FileSize": 0,
      "LastModified": "",
      "IsSelectable": true,
      "Properties": {}
    },
    {
      "Id": "GlobalObjectId_V1-1-52ce23d6820ebbd4588456dd3c944df9-2800000-0",
      "Label": "",
      "Description": "",
      "Provider": "asset",
      "Type": "Asset",
      "Path": "Assets/SU3DJPFont/Fonts/MPlusTestflight63a/mplus-2p-regular.ttf",
      "Thumbnail": "",
      "Score": 109.0,
      "Tags": [
        "asset"
      ],
      "FileSize": 0,
      "LastModified": "",
      "IsSelectable": true,
      "Properties": {}
    },
    {
      "Id": "GlobalObjectId_V1-1-550e39a93bdf11c4eb1ab20d722406be-2800000-0",
      "Label": "",
      "Description": "",
      "Provider": "asset",
      "Type": "Asset",
      "Path": "Assets/SU3DJPFont/Fonts/MPlusTestflight63a/mplus-2c-bold.ttf",
      "Thumbnail": "",
      "Score": 109.0,
      "Tags": [
        "asset"
      ],
      "FileSize": 0,
      "LastModified": "",
      "IsSelectable": true,
      "Properties": {}
    },
    {
      "Id": "GlobalObjectId_V1-1-57c92973c1933254089ea5b3c48adf65-2800000-0",
      "Label": "",
      "Description": "",
      "Provider": "asset",
      "Type": "Asset",
      "Path": "Assets/SU3DJPFont/Fonts/MPlusTestflight63a/mplus-2p-light.ttf",
      "Thumbnail": "",
      "Score": 109.0,
      "Tags": [
        "asset"
      ],
      "FileSize": 0,
      "LastModified": "",
      "IsSelectable": true,
      "Properties": {}
    },
    {
      "Id": "GlobalObjectId_V1-1-5b510769ddba50845a81da25103a8b73-2800000-0",
      "Label": "",
      "Description": "",
      "Provider": "asset",
      "Type": "Asset",
      "Path": "Assets/SU3DJPFont/Fonts/MPlusTestflight63a/mplus-1m-regular.ttf",
      "Thumbnail": "",
      "Score": 109.0,
      "Tags": [
        "asset"
      ],
      "FileSize": 0,
      "LastModified": "",
      "IsSelectable": true,
      "Properties": {}
    },
    {
      "Id": "GlobalObjectId_V1-1-5f3edff6d7c989d42855196f819dd804-2800000-0",
      "Label": "",
      "Description": "",
      "Provider": "asset",
      "Type": "Asset",
      "Path": "Assets/SU3DJPFont/Fonts/MPlusTestflight63a/mplus-1c-thin.ttf",
      "Thumbnail": "",
      "Score": 109.0,
      "Tags": [
        "asset"
      ],
      "FileSize": 0,
      "LastModified": "",
      "IsSelectable": true,
      "Properties": {}
    },
    {
      "Id": "GlobalObjectId_V1-1-5fc14a699a1d36a4a8ae87d331d5ca6b-2800000-0",
      "Label": "",
      "Description": "",
      "Provider": "asset",
      "Type": "Asset",
      "Path": "Assets/SU3DJPFont/Fonts/MPlusTestflight63a/mplus-1c-light.ttf",
      "Thumbnail": "",
      "Score": 109.0,
      "Tags": [
        "asset"
      ],
      "FileSize": 0,
      "LastModified": "",
      "IsSelectable": true,
      "Properties": {}
    },
    {
      "Id": "GlobalObjectId_V1-1-61becaa4fedde64479b92990d9ceb0e7-2800000-0",
      "Label": "",
      "Description": "",
      "Provider": "asset",
      "Type": "Asset",
      "Path": "Assets/SU3DJPFont/Fonts/MPlusTestflight63a/mplus-1mn-bold.ttf",
      "Thumbnail": "",
      "Score": 109.0,
      "Tags": [
        "asset"
      ],
      "FileSize": 0,
      "LastModified": "",
      "IsSelectable": true,
      "Properties": {}
    },
    {
      "Id": "GlobalObjectId_V1-1-693633b0f26082e4a9cb35d1f8fe5c50-2800000-0",
      "Label": "",
      "Description": "",
      "Provider": "asset",
      "Type": "Asset",
      "Path": "Assets/SU3DJPFont/Fonts/MPlusTestflight63a/mplus-1mn-medium.ttf",
      "Thumbnail": "",
      "Score": 109.0,
      "Tags": [
        "asset"
      ],
      "FileSize": 0,
      "LastModified": "",
      "IsSelectable": true,
      "Properties": {}
    },
    {
      "Id": "GlobalObjectId_V1-1-6f1de2168b8b1de499b7aa122334162e-2800000-0",
      "Label": "",
      "Description": "",
      "Provider": "asset",
      "Type": "Asset",
      "Path": "Assets/SU3DJPFont/Fonts/MPlusTestflight63a/mplus-1c-medium.ttf",
      "Thumbnail": "",
      "Score": 109.0,
      "Tags": [
        "asset"
      ],
      "FileSize": 0,
      "LastModified": "",
      "IsSelectable": true,
      "Properties": {}
    },
    {
      "Id": "GlobalObjectId_V1-1-713ad0fc8788e4843a05a1e67be11b74-2800000-0",
      "Label": "",
      "Description": "",
      "Provider": "asset",
      "Type": "Asset",
      "Path": "Assets/SU3DJPFont/Fonts/MPlusTestflight63a/mplus-2p-black.ttf",
      "Thumbnail": "",
      "Score": 109.0,
      "Tags": [
        "asset"
      ],
      "FileSize": 0,
      "LastModified": "",
      "IsSelectable": true,
      "Properties": {}
    },
    {
      "Id": "GlobalObjectId_V1-1-7a744464177b17945a83e77b87e70d5e-2800000-0",
      "Label": "",
      "Description": "",
      "Provider": "asset",
      "Type": "Asset",
      "Path": "Assets/SU3DJPFont/Fonts/MPlusTestflight63a/mplus-2c-regular.ttf",
      "Thumbnail": "",
      "Score": 109.0,
      "Tags": [
        "asset"
      ],
      "FileSize": 0,
      "LastModified": "",
      "IsSelectable": true,
      "Properties": {}
    },
    {
      "Id": "GlobalObjectId_V1-1-8a30ff51f11ad8641b65063283610191-2800000-0",
      "Label": "",
      "Description": "",
      "Provider": "asset",
      "Type": "Asset",
      "Path": "Assets/SU3DJPFont/Fonts/MPlusTestflight63a/mplus-1mn-regular.ttf",
      "Thumbnail": "",
      "Score": 109.0,
      "Tags": [
        "asset"
      ],
      "FileSize": 0,
      "LastModified": "",
      "IsSelectable": true,
      "Properties": {}
    },
    {
      "Id": "GlobalObjectId_V1-1-8d804c8863accb0458362d2fa96ac648-2800000-0",
      "Label": "",
      "Description": "",
      "Provider": "asset",
      "Type": "Asset",
      "Path": "Assets/SU3DJPFont/Fonts/MPlusTestflight63a/mplus-1m-medium.ttf",
      "Thumbnail": "",
      "Score": 109.0,
      "Tags": [
        "asset"
      ],
      "FileSize": 0,
      "LastModified": "",
      "IsSelectable": true,
      "Properties": {}
    },
    {
      "Id": "GlobalObjectId_V1-1-957961a2f2fb44042809544e043b69c8-2800000-0",
      "Label": "",
      "Description": "",
      "Provider": "asset",
      "Type": "Asset",
      "Path": "Assets/SU3DJPFont/Fonts/MPlusTestflight63a/mplus-2p-bold.ttf",
      "Thumbnail": "",
      "Score": 109.0,
      "Tags": [
        "asset"
      ],
      "FileSize": 0,
      "LastModified": "",
      "IsSelectable": true,
      "Properties": {}
    },
    {
      "Id": "GlobalObjectId_V1-1-9d4178bd3264b6243a243a254b89f286-2800000-0",
      "Label": "",
      "Description": "",
      "Provider": "asset",
      "Type": "Asset",
      "Path": "Assets/SU3DJPFont/Fonts/MPlusTestflight63a/mplus-1p-heavy.ttf",
      "Thumbnail": "",
      "Score": 109.0,
      "Tags": [
        "asset"
      ],
      "FileSize": 0,
      "LastModified": "",
      "IsSelectable": true,
      "Properties": {}
    },
    {
      "Id": "GlobalObjectId_V1-1-9eae05575b38e1740ac305d86ca76031-2800000-0",
      "Label": "",
      "Description": "",
      "Provider": "asset",
      "Type": "Asset",
      "Path": "Assets/SU3DJPFont/Fonts/MPlusTestflight63a/mplus-1p-light.ttf",
      "Thumbnail": "",
      "Score": 109.0,
      "Tags": [
        "asset"
      ],
      "FileSize": 0,
      "LastModified": "",
      "IsSelectable": true,
      "Properties": {}
    },
    {
      "Id": "GlobalObjectId_V1-1-a2e1135d37c3552429765a3d54afffef-2800000-0",
      "Label": "",
      "Description": "",
      "Provider": "asset",
      "Type": "Asset",
      "Path": "Assets/SU3DJPFont/Fonts/MPlusTestflight63a/mplus-1c-regular.ttf",
      "Thumbnail": "",
      "Score": 109.0,
      "Tags": [
        "asset"
      ],
      "FileSize": 0,
      "LastModified": "",
      "IsSelectable": true,
      "Properties": {}
    },
    {
      "Id": "GlobalObjectId_V1-1-a64c8a307d22d6e4e8266a7c8d2911d5-2800000-0",
      "Label": "",
      "Description": "",
      "Provider": "asset",
      "Type": "Asset",
      "Path": "Assets/SU3DJPFont/Fonts/MPlusTestflight63a/mplus-1m-thin.ttf",
      "Thumbnail": "",
      "Score": 109.0,
      "Tags": [
        "asset"
      ],
      "FileSize": 0,
      "LastModified": "",
      "IsSelectable": true,
      "Properties": {}
    },
    {
      "Id": "GlobalObjectId_V1-1-aacf6a09bbf1e664788c2744ab470681-2800000-0",
      "Label": "",
      "Description": "",
      "Provider": "asset",
      "Type": "Asset",
      "Path": "Assets/SU3DJPFont/Fonts/MPlusTestflight63a/mplus-2p-thin.ttf",
      "Thumbnail": "",
      "Score": 109.0,
      "Tags": [
        "asset"
      ],
      "FileSize": 0,
      "LastModified": "",
      "IsSelectable": true,
      "Properties": {}
    },
    {
      "Id": "GlobalObjectId_V1-1-b094e267f0d6a8341815a7eca30f04fa-2800000-0",
      "Label": "",
      "Description": "",
      "Provider": "asset",
      "Type": "Asset",
      "Path": "Assets/SU3DJPFont/Fonts/MPlusTestflight63a/mplus-1m-light.ttf",
      "Thumbnail": "",
      "Score": 109.0,
      "Tags": [
        "asset"
      ],
      "FileSize": 0,
      "LastModified": "",
      "IsSelectable": true,
      "Properties": {}
    },
    {
      "Id": "GlobalObjectId_V1-1-bb7bf971099b1c14aa43c44bd24fc573-2800000-0",
      "Label": "",
      "Description": "",
      "Provider": "asset",
      "Type": "Asset",
      "Path": "Assets/SU3DJPFont/Fonts/MPlusTestflight63a/mplus-1p-regular.ttf",
      "Thumbnail": "",
      "Score": 109.0,
      "Tags": [
        "asset"
      ],
      "FileSize": 0,
      "LastModified": "",
      "IsSelectable": true,
      "Properties": {}
    },
    {
      "Id": "GlobalObjectId_V1-1-bdb6cca785a51c2418e27f3da4b87587-2800000-0",
      "Label": "",
      "Description": "",
      "Provider": "asset",
      "Type": "Asset",
      "Path": "Assets/SU3DJPFont/Fonts/MPlusTestflight63a/mplus-1c-heavy.ttf",
      "Thumbnail": "",
      "Score": 109.0,
      "Tags": [
        "asset"
      ],
      "FileSize": 0,
      "LastModified": "",
      "IsSelectable": true,
      "Properties": {}
    },
    {
      "Id": "GlobalObjectId_V1-1-bf882ea178a999648a63680a4a04ac5d-2800000-0",
      "Label": "",
      "Description": "",
      "Provider": "asset",
      "Type": "Asset",
      "Path": "Assets/SU3DJPFont/Fonts/MPlusTestflight63a/mplus-1c-black.ttf",
      "Thumbnail": "",
      "Score": 109.0,
      "Tags": [
        "asset"
      ],
      "FileSize": 0,
      "LastModified": "",
      "IsSelectable": true,
      "Properties": {}
    },
    {
      "Id": "GlobalObjectId_V1-1-c0d30712f09cc2649b1487cc257bf235-2800000-0",
      "Label": "",
      "Description": "",
      "Provider": "asset",
      "Type": "Asset",
      "Path": "Assets/SU3DJPFont/Fonts/MPlusTestflight63a/mplus-2m-medium.ttf",
      "Thumbnail": "",
      "Score": 109.0,
      "Tags": [
        "asset"
      ],
      "FileSize": 0,
      "LastModified": "",
      "IsSelectable": true,
      "Properties": {}
    },
    {
      "Id": "GlobalObjectId_V1-1-c24573627499dc340929d2c48a140632-2800000-0",
      "Label": "",
      "Description": "",
      "Provider": "asset",
      "Type": "Asset",
      "Path": "Assets/SU3DJPFont/Fonts/MPlusTestflight63a/mplus-1m-bold.ttf",
      "Thumbnail": "",
      "Score": 109.0,
      "Tags": [
        "asset"
      ],
      "FileSize": 0,
      "LastModified": "",
      "IsSelectable": true,
      "Properties": {}
    },
    {
      "Id": "GlobalObjectId_V1-1-d22d91c285ac82849bc2563a6707d20b-2800000-0",
      "Label": "",
      "Description": "",
      "Provider": "asset",
      "Type": "Asset",
      "Path": "Assets/SU3DJPFont/Fonts/MPlusTestflight63a/mplus-1p-bold.ttf",
      "Thumbnail": "",
      "Score": 109.0,
      "Tags": [
        "asset"
      ],
      "FileSize": 0,
      "LastModified": "",
      "IsSelectable": true,
      "Properties": {}
    },
    {
      "Id": "GlobalObjectId_V1-1-d2af8c7e8b712bb4a956d8ddca140d02-2800000-0",
      "Label": "",
      "Description": "",
      "Provider": "asset",
      "Type": "Asset",
      "Path": "Assets/SU3DJPFont/Fonts/MPlusTestflight63a/mplus-2p-heavy.ttf",
      "Thumbnail": "",
      "Score": 109.0,
      "Tags": [
        "asset"
      ],
      "FileSize": 0,
      "LastModified": "",
      "IsSelectable": true,
      "Properties": {}
    },
    {
      "Id": "GlobalObjectId_V1-1-e1ad4755b7977484ca371b50c9b219d1-2800000-0",
      "Label": "",
      "Description": "",
      "Provider": "asset",
      "Type": "Asset",
      "Path": "Assets/SU3DJPFont/Fonts/MPlusTestflight63a/mplus-1p-black.ttf",
      "Thumbnail": "",
      "Score": 109.0,
      "Tags": [
        "asset"
      ],
      "FileSize": 0,
      "LastModified": "",
      "IsSelectable": true,
      "Properties": {}
    },
    {
      "Id": "GlobalObjectId_V1-1-e21d4af4ada4a1442bcb27262f4c20a0-2800000-0",
      "Label": "",
      "Description": "",
      "Provider": "asset",
      "Type": "Asset",
      "Path": "Assets/SU3DJPFont/Fonts/MPlusTestflight63a/mplus-2c-medium.ttf",
      "Thumbnail": "",
      "Score": 109.0,
      "Tags": [
        "asset"
      ],
      "FileSize": 0,
      "LastModified": "",
      "IsSelectable": true,
      "Properties": {}
    },
    {
      "Id": "GlobalObjectId_V1-1-ed37ac09b7b397d499d47b77861e2fe3-2800000-0",
      "Label": "",
      "Description": "",
      "Provider": "asset",
      "Type": "Asset",
      "Path": "Assets/SU3DJPFont/Fonts/MPlusTestflight63a/mplus-2c-black.ttf",
      "Thumbnail": "",
      "Score": 109.0,
      "Tags": [
        "asset"
      ],
      "FileSize": 0,
      "LastModified": "",
      "IsSelectable": true,
      "Properties": {}
    },
    {
      "Id": "GlobalObjectId_V1-1-ef284d01c8f49b74595294c5f4296784-2800000-0",
      "Label": "",
      "Description": "",
      "Provider": "asset",
      "Type": "Asset",
      "Path": "Assets/SU3DJPFont/Fonts/MPlusTestflight63a/mplus-1p-medium.ttf",
      "Thumbnail": "",
      "Score": 109.0,
      "Tags": [
        "asset"
      ],
      "FileSize": 0,
      "LastModified": "",
      "IsSelectable": true,
      "Properties": {}
    },
    {
      "Id": "GlobalObjectId_V1-1-f6addef24a2887245854cacb60838807-2800000-0",
      "Label": "",
      "Description": "",
      "Provider": "asset",
      "Type": "Asset",
      "Path": "Assets/Particlecollection_Free samples/Texture/magic_01.png",
      "Thumbnail": "",
      "Score": 109.0,
      "Tags": [
        "asset"
      ],
      "FileSize": 0,
      "LastModified": "",
      "IsSelectable": true,
      "Properties": {}
    },
    {
      "Id": "GlobalObjectId_V1-1-f82f6e0d549c45c4396246185a462e1d-2800000-0",
      "Label": "",
      "Description": "",
      "Provider": "asset",
      "Type": "Asset",
      "Path": "Assets/SU3DJPFont/Fonts/MPlusTestflight63a/mplus-2c-thin.ttf",
      "Thumbnail": "",
      "Score": 109.0,
      "Tags": [
        "asset"
      ],
      "FileSize": 0,
      "LastModified": "",
      "IsSelectable": true,
      "Properties": {}
    },
    {
      "Id": "GlobalObjectId_V1-3-009e09fc66848ab4fa3d6b116e18dafa-28616853068833048-0",
      "Label": "",
      "Description": "",
      "Provider": "asset",
      "Type": "Asset",
      "Path": "Assets/SU3DJPFont/TextMeshProFont/Selected/mplus-1p-thin SDF.asset",
      "Thumbnail": "",
      "Score": 109.0,
      "Tags": [
        "asset"
      ],
      "FileSize": 0,
      "LastModified": "",
      "IsSelectable": true,
      "Properties": {}
    },
    {
      "Id": "GlobalObjectId_V1-3-026df6568a42045439ef34913f798f6f-16722643928791675555-0",
      "Label": "",
      "Description": "",
      "Provider": "asset",
      "Type": "Asset",
      "Path": "Assets/SU3DJPFont/TextMeshProFont/Dynamic/mplus-1p-medium SDF Dynamic.asset",
      "Thumbnail": "",
      "Score": 109.0,
      "Tags": [
        "asset"
      ],
      "FileSize": 0,
      "LastModified": "",
      "IsSelectable": true,
      "Properties": {}
    },
    {
      "Id": "GlobalObjectId_V1-3-07f123dbf7500654da7928434dafbb13-28975501552777804-0",
      "Label": "",
      "Description": "",
      "Provider": "asset",
      "Type": "Asset",
      "Path": "Assets/SU3DJPFont/TextMeshProFont/Selected/mplus-1m-medium SDF.asset",
      "Thumbnail": "",
      "Score": 109.0,
      "Tags": [
        "asset"
      ],
      "FileSize": 0,
      "LastModified": "",
      "IsSelectable": true,
      "Properties": {}
    },
    {
      "Id": "GlobalObjectId_V1-3-08da0bd69441860428c853b63835cdbe-28668833011503328-0",
      "Label": "",
      "Description": "",
      "Provider": "asset",
      "Type": "Asset",
      "Path": "Assets/SU3DJPFont/TextMeshProFont/Selected/mplus-1mn-medium SDF.asset",
      "Thumbnail": "",
      "Score": 109.0,
      "Tags": [
        "asset"
      ],
      "FileSize": 0,
      "LastModified": "",
      "IsSelectable": true,
      "Properties": {}
    },
    {
      "Id": "GlobalObjectId_V1-3-09bb5f87b12efc743871ab9dee64c0d6-28357497816193732-0",
      "Label": "",
      "Description": "",
      "Provider": "asset",
      "Type": "Asset",
      "Path": "Assets/SU3DJPFont/TextMeshProFont/Selected/mplus-1mn-bold SDF.asset",
      "Thumbnail": "",
      "Score": 109.0,
      "Tags": [
        "asset"
      ],
      "FileSize": 0,
      "LastModified": "",
      "IsSelectable": true,
      "Properties": {}
    },
    {
      "Id": "GlobalObjectId_V1-3-0a60499eecd1b4e4889b36c308d2c9af-12548822369638525125-0",
      "Label": "",
      "Description": "",
      "Provider": "asset",
      "Type": "Asset",
      "Path": "Assets/SU3DJPFont/TextMeshProFont/Dynamic/mplus-1c-thin SDF Dynamic.asset",
      "Thumbnail": "",
      "Score": 109.0,
      "Tags": [
        "asset"
      ],
      "FileSize": 0,
      "LastModified": "",
      "IsSelectable": true,
      "Properties": {}
    },
    {
      "Id": "GlobalObjectId_V1-3-0e11ec24410208247973f09687fd7697-13070397149437511692-0",
      "Label": "",
      "Description": "",
      "Provider": "asset",
      "Type": "Asset",
      "Path": "Assets/SU3DJPFont/TextMeshProFont/Dynamic/mplus-2p-thin SDF Dynamic.asset",
      "Thumbnail": "",
      "Score": 109.0,
      "Tags": [
        "asset"
      ],
      "FileSize": 0,
      "LastModified": "",
      "IsSelectable": true,
      "Properties": {}
    },
    {
      "Id": "GlobalObjectId_V1-3-0ff6df91eb3690a4d9dc9311e6850c55-9814035559181321607-0",
      "Label": "",
      "Description": "",
      "Provider": "asset",
      "Type": "Asset",
      "Path": "Assets/SU3DJPFont/TextMeshProFont/Dynamic/mplus-2m-medium SDF Dynamic.asset",
      "Thumbnail": "",
      "Score": 109.0,
      "Tags": [
        "asset"
      ],
      "FileSize": 0,
      "LastModified": "",
      "IsSelectable": true,
      "Properties": {}
    },
    {
      "Id": "GlobalObjectId_V1-3-122fd77c99b4c11418c5b92968e30e01-28868149325195638-0",
      "Label": "",
      "Description": "",
      "Provider": "asset",
      "Type": "Asset",
      "Path": "Assets/SU3DJPFont/TextMeshProFont/Selected/mplus-2m-bold SDF.asset",
      "Thumbnail": "",
      "Score": 109.0,
      "Tags": [
        "asset"
      ],
      "FileSize": 0,
      "LastModified": "",
      "IsSelectable": true,
      "Properties": {}
    },
    {
      "Id": "GlobalObjectId_V1-3-12c27379b39e44346813b13ec333d516-28982734707070348-0",
      "Label": "",
      "Description": "",
      "Provider": "asset",
      "Type": "Asset",
      "Path": "Assets/SU3DJPFont/TextMeshProFont/Selected/mplus-1c-black SDF.asset",
      "Thumbnail": "",
      "Score": 109.0,
      "Tags": [
        "asset"
      ],
      "FileSize": 0,
      "LastModified": "",
      "IsSelectable": true,
      "Properties": {}
    },
    {
      "Id": "GlobalObjectId_V1-3-1447738d5ea80244f8423ebedc6e8612-28175047149046614-0",
      "Label": "",
      "Description": "",
      "Provider": "asset",
      "Type": "Asset",
      "Path": "Assets/SU3DJPFont/TextMeshProFont/Selected/mplus-1m-light SDF.asset",
      "Thumbnail": "",
      "Score": 109.0,
      "Tags": [
        "asset"
      ],
      "FileSize": 0,
      "LastModified": "",
      "IsSelectable": true,
      "Properties": {}
    },
    {
      "Id": "GlobalObjectId_V1-3-18c9325df09bcc14e8d026e73f268825-5911340561608254510-0",
      "Label": "",
      "Description": "",
      "Provider": "asset",
      "Type": "Asset",
      "Path": "Assets/SU3DJPFont/TextMeshProFont/Dynamic/mplus-1m-medium SDF Dynamic.asset",
      "Thumbnail": "",
      "Score": 109.0,
      "Tags": [
        "asset"
      ],
      "FileSize": 0,
      "LastModified": "",
      "IsSelectable": true,
      "Properties": {}
    },
    {
      "Id": "GlobalObjectId_V1-3-1b49521a593780140ab98a5973e9712d-11787329273126134810-0",
      "Label": "",
      "Description": "",
      "Provider": "asset",
      "Type": "Asset",
      "Path": "Assets/SU3DJPFont/TextMeshProFont/Dynamic/mplus-1c-light SDF Dynamic.asset",
      "Thumbnail": "",
      "Score": 109.0,
      "Tags": [
        "asset"
      ],
      "FileSize": 0,
      "LastModified": "",
      "IsSelectable": true,
      "Properties": {}
    },
    {
      "Id": "GlobalObjectId_V1-3-1c83e3436f94f3e4a8e634392f75652a-2130075201995888061-0",
      "Label": "",
      "Description": "",
      "Provider": "asset",
      "Type": "Asset",
      "Path": "Assets/SU3DJPFont/TextMeshProFont/Dynamic/mplus-1m-bold SDF Dynamic.asset",
      "Thumbnail": "",
      "Score": 109.0,
      "Tags": [
        "asset"
      ],
      "FileSize": 0,
      "LastModified": "",
      "IsSelectable": true,
      "Properties": {}
    },
    {
      "Id": "GlobalObjectId_V1-3-254846f4ed1a55047b794ef5c57e9ae3-28549573968816030-0",
      "Label": "",
      "Description": "",
      "Provider": "asset",
      "Type": "Asset",
      "Path": "Assets/SU3DJPFont/TextMeshProFont/Selected/mplus-2p-thin SDF.asset",
      "Thumbnail": "",
      "Score": 109.0,
      "Tags": [
        "asset"
      ],
      "FileSize": 0,
      "LastModified": "",
      "IsSelectable": true,
      "Properties": {}
    },
    {
      "Id": "GlobalObjectId_V1-3-260ee7a26c62f474c8ea5be16a214677-28496916933132110-0",
      "Label": "",
      "Description": "",
      "Provider": "asset",
      "Type": "Asset",
      "Path": "Assets/SU3DJPFont/TextMeshProFont/Selected/mplus-2c-thin SDF.asset",
      "Thumbnail": "",
      "Score": 109.0,
      "Tags": [
        "asset"
      ],
      "FileSize": 0,
      "LastModified": "",
      "IsSelectable": true,
      "Properties": {}
    },
    {
      "Id": "GlobalObjectId_V1-3-2969ca695cdb331458afd7e08ea97c82-17452502565309602013-0",
      "Label": "",
      "Description": "",
      "Provider": "asset",
      "Type": "Asset",
      "Path": "Assets/SU3DJPFont/TextMeshProFont/Dynamic/mplus-2m-thin SDF Dynamic.asset",
      "Thumbnail": "",
      "Score": 109.0,
      "Tags": [
        "asset"
      ],
      "FileSize": 0,
      "LastModified": "",
      "IsSelectable": true,
      "Properties": {}
    },
    {
      "Id": "GlobalObjectId_V1-3-2ac9913cb1b50c44b8b4f382b0e00550-8804081343568962584-0",
      "Label": "",
      "Description": "",
      "Provider": "asset",
      "Type": "Asset",
      "Path": "Assets/SU3DJPFont/TextMeshProFont/Dynamic/mplus-1p-light SDF Dynamic.asset",
      "Thumbnail": "",
      "Score": 109.0,
      "Tags": [
        "asset"
      ],
      "FileSize": 0,
      "LastModified": "",
      "IsSelectable": true,
      "Properties": {}
    },
    {
      "Id": "GlobalObjectId_V1-3-2b3dd3afc421f9d44bd2945344e7c04c-28931325954400560-0",
      "Label": "",
      "Description": "",
      "Provider": "asset",
      "Type": "Asset",
      "Path": "Assets/SU3DJPFont/TextMeshProFont/Selected/mplus-1p-bold SDF.asset",
      "Thumbnail": "",
      "Score": 109.0,
      "Tags": [
        "asset"
      ],
      "FileSize": 0,
      "LastModified": "",
      "IsSelectable": true,
      "Properties": {}
    },
    {
      "Id": "GlobalObjectId_V1-3-30349895a8d181f48906005bb7b34ec9-28277097941532274-0",
      "Label": "",
      "Description": "",
      "Provider": "asset",
      "Type": "Asset",
      "Path": "Assets/SU3DJPFont/TextMeshProFont/Selected/mplus-1m-thin SDF.asset",
      "Thumbnail": "",
      "Score": 109.0,
      "Tags": [
        "asset"
      ],
      "FileSize": 0,
      "LastModified": "",
      "IsSelectable": true,
      "Properties": {}
    },
    {
      "Id": "GlobalObjectId_V1-3-31f8b3fb793f1c748bc6d7d30a21a929-28535022998961896-0",
      "Label": "",
      "Description": "",
      "Provider": "asset",
      "Type": "Asset",
      "Path": "Assets/SU3DJPFont/TextMeshProFont/Selected/mplus-2c-medium SDF.asset",
      "Thumbnail": "",
      "Score": 109.0,
      "Tags": [
        "asset"
      ],
      "FileSize": 0,
      "LastModified": "",
      "IsSelectable": true,
      "Properties": {}
    },
    {
      "Id": "GlobalObjectId_V1-3-38f325ed71ced0647824d8aa1adf1e21-17153807208524055588-0",
      "Label": "",
      "Description": "",
      "Provider": "asset",
      "Type": "Asset",
      "Path": "Assets/SU3DJPFont/TextMeshProFont/Dynamic/mplus-1mn-bold SDF Dynamic.asset",
      "Thumbnail": "",
      "Score": 109.0,
      "Tags": [
        "asset"
      ],
      "FileSize": 0,
      "LastModified": "",
      "IsSelectable": true,
      "Properties": {}
    },
    {
      "Id": "GlobalObjectId_V1-3-3efee4f854459214f87fc6f32795320a-13859941124183907231-0",
      "Label": "",
      "Description": "",
      "Provider": "asset",
      "Type": "Asset",
      "Path": "Assets/SU3DJPFont/TextMeshProFont/Dynamic/mplus-1c-medium SDF Dynamic.asset",
      "Thumbnail": "",
      "Score": 109.0,
      "Tags": [
        "asset"
      ],
      "FileSize": 0,
      "LastModified": "",
      "IsSelectable": true,
      "Properties": {}
    },
    {
      "Id": "GlobalObjectId_V1-3-485926a3a0f8f154a8d88a9dc497e850-28862727794817542-0",
      "Label": "",
      "Description": "",
      "Provider": "asset",
      "Type": "Asset",
      "Path": "Assets/SU3DJPFont/TextMeshProFont/Selected/mplus-1c-heavy SDF.asset",
      "Thumbnail": "",
      "Score": 109.0,
      "Tags": [
        "asset"
      ],
      "FileSize": 0,
      "LastModified": "",
      "IsSelectable": true,
      "Properties": {}
    },
    {
      "Id": "GlobalObjectId_V1-3-5d1e22d4f8cc6634cba9e8a034126ae8-28139038539194958-0",
      "Label": "",
      "Description": "",
      "Provider": "asset",
      "Type": "Asset",
      "Path": "Assets/SU3DJPFont/TextMeshProFont/Selected/mplus-2m-thin SDF.asset",
      "Thumbnail": "",
      "Score": 109.0,
      "Tags": [
        "asset"
      ],
      "FileSize": 0,
      "LastModified": "",
      "IsSelectable": true,
      "Properties": {}
    },
    {
      "Id": "GlobalObjectId_V1-3-5d826aa60a375a344ae83ecbed1e90ce-15209465287235221545-0",
      "Label": "",
      "Description": "",
      "Provider": "asset",
      "Type": "Asset",
      "Path": "Assets/SU3DJPFont/TextMeshProFont/Dynamic/mplus-1mn-regular SDF Dynamic.asset",
      "Thumbnail": "",
      "Score": 109.0,
      "Tags": [
        "asset"
      ],
      "FileSize": 0,
      "LastModified": "",
      "IsSelectable": true,
      "Properties": {}
    },
    {
      "Id": "GlobalObjectId_V1-3-5d9fd4cc1d3d4e64d8f49020f6f51b36-28159942116451910-0",
      "Label": "",
      "Description": "",
      "Provider": "asset",
      "Type": "Asset",
      "Path": "Assets/SU3DJPFont/TextMeshProFont/Selected/mplus-1c-regular SDF.asset",
      "Thumbnail": "",
      "Score": 109.0,
      "Tags": [
        "asset"
      ],
      "FileSize": 0,
      "LastModified": "",
      "IsSelectable": true,
      "Properties": {}
    },
    {
      "Id": "GlobalObjectId_V1-3-5e76a04e4dce38848a1acc4580589be8-15248010312664450662-0",
      "Label": "",
      "Description": "",
      "Provider": "asset",
      "Type": "Asset",
      "Path": "Assets/SU3DJPFont/TextMeshProFont/Dynamic/mplus-2c-light SDF Dynamic.asset",
      "Thumbnail": "",
      "Score": 109.0,
      "Tags": [
        "asset"
      ],
      "FileSize": 0,
      "LastModified": "",
      "IsSelectable": true,
      "Properties": {}
    },
    {
      "Id": "GlobalObjectId_V1-3-63fc1fdea266fce49a93f347f02e3389-28337747821023926-0",
      "Label": "",
      "Description": "",
      "Provider": "asset",
      "Type": "Asset",
      "Path": "Assets/SU3DJPFont/TextMeshProFont/Selected/mplus-1c-thin SDF.asset",
      "Thumbnail": "",
      "Score": 109.0,
      "Tags": [
        "asset"
      ],
      "FileSize": 0,
      "LastModified": "",
      "IsSelectable": true,
      "Properties": {}
    },
    {
      "Id": "GlobalObjectId_V1-3-6628e6c3d971ee34f89d02292ab473ed-28093561432766106-0",
      "Label": "",
      "Description": "",
      "Provider": "asset",
      "Type": "Asset",
      "Path": "Assets/SU3DJPFont/TextMeshProFont/Selected/mplus-2p-heavy SDF.asset",
      "Thumbnail": "",
      "Score": 109.0,
      "Tags": [
        "asset"
      ],
      "FileSize": 0,
      "LastModified": "",
      "IsSelectable": true,
      "Properties": {}
    },
    {
      "Id": "GlobalObjectId_V1-3-69235bbac6067234daeb5c3fe82df89c-28645340762724930-0",
      "Label": "",
      "Description": "",
      "Provider": "asset",
      "Type": "Asset",
      "Path": "Assets/SU3DJPFont/TextMeshProFont/Selected/mplus-1p-light SDF.asset",
      "Thumbnail": "",
      "Score": 109.0,
      "Tags": [
        "asset"
      ],
      "FileSize": 0,
      "LastModified": "",
      "IsSelectable": true,
      "Properties": {}
    },
    {
      "Id": "GlobalObjectId_V1-3-6a7dd9f2b8eaaa047b0af326ecc5a170-6117869515687762199-0",
      "Label": "",
      "Description": "",
      "Provider": "asset",
      "Type": "Asset",
      "Path": "Assets/SU3DJPFont/TextMeshProFont/Dynamic/mplus-1mn-light SDF Dynamic.asset",
      "Thumbnail": "",
      "Score": 109.0,
      "Tags": [
        "asset"
      ],
      "FileSize": 0,
      "LastModified": "",
      "IsSelectable": true,
      "Properties": {}
    },
    {
      "Id": "GlobalObjectId_V1-3-6bd09f3074e111f48b61b0ea95020654-28397187507354644-0",
      "Label": "",
      "Description": "",
      "Provider": "asset",
      "Type": "Asset",
      "Path": "Assets/SU3DJPFont/TextMeshProFont/Selected/mplus-2c-heavy SDF.asset",
      "Thumbnail": "",
      "Score": 109.0,
      "Tags": [
        "asset"
      ],
      "FileSize": 0,
      "LastModified": "",
      "IsSelectable": true,
      "Properties": {}
    },
    {
      "Id": "GlobalObjectId_V1-3-6d52bac519b2d9642a9989eda8b36b18-28641149654606980-0",
      "Label": "",
      "Description": "",
      "Provider": "asset",
      "Type": "Asset",
      "Path": "Assets/SU3DJPFont/TextMeshProFont/Selected/mplus-1p-black SDF.asset",
      "Thumbnail": "",
      "Score": 109.0,
      "Tags": [
        "asset"
      ],
      "FileSize": 0,
      "LastModified": "",
      "IsSelectable": true,
      "Properties": {}
    },
    {
      "Id": "GlobalObjectId_V1-3-6f27848c0a0f6284aad6e3cb3817e07b-28482849273124622-0",
      "Label": "",
      "Description": "",
      "Provider": "asset",
      "Type": "Asset",
      "Path": "Assets/SU3DJPFont/TextMeshProFont/Selected/mplus-1p-medium SDF.asset",
      "Thumbnail": "",
      "Score": 109.0,
      "Tags": [
        "asset"
      ],
      "FileSize": 0,
      "LastModified": "",
      "IsSelectable": true,
      "Properties": {}
    },
    {
      "Id": "GlobalObjectId_V1-3-6f29556881f728c4f8190848e4538fb9-28282133034188604-0",
      "Label": "",
      "Description": "",
      "Provider": "asset",
      "Type": "Asset",
      "Path": "Assets/SU3DJPFont/TextMeshProFont/Selected/mplus-2p-regular SDF.asset",
      "Thumbnail": "",
      "Score": 109.0,
      "Tags": [
        "asset"
      ],
      "FileSize": 0,
      "LastModified": "",
      "IsSelectable": true,
      "Properties": {}
    },
    {
      "Id": "GlobalObjectId_V1-3-7106e4f34c7264842b2223224b337d80-7858535117429185323-0",
      "Label": "",
      "Description": "",
      "Provider": "asset",
      "Type": "Asset",
      "Path": "Assets/SU3DJPFont/TextMeshProFont/Dynamic/mplus-1p-bold SDF Dynamic.asset",
      "Thumbnail": "",
      "Score": 109.0,
      "Tags": [
        "asset"
      ],
      "FileSize": 0,
      "LastModified": "",
      "IsSelectable": true,
      "Properties": {}
    },
    {
      "Id": "GlobalObjectId_V1-3-71de30c1f9d8dc846bd433d0857acd1d-5491734472926921193-0",
      "Label": "",
      "Description": "",
      "Provider": "asset",
      "Type": "Asset",
      "Path": "Assets/SU3DJPFont/TextMeshProFont/Dynamic/mplus-2p-heavy SDF Dynamic.asset",
      "Thumbnail": "",
      "Score": 109.0,
      "Tags": [
        "asset"
      ],
      "FileSize": 0,
      "LastModified": "",
      "IsSelectable": true,
      "Properties": {}
    },
    {
      "Id": "GlobalObjectId_V1-3-73efd110800510942a8bc409055d4711-8180487629889406186-0",
      "Label": "",
      "Description": "",
      "Provider": "asset",
      "Type": "Asset",
      "Path": "Assets/SU3DJPFont/TextMeshProFont/Dynamic/mplus-2p-medium SDF Dynamic.asset",
      "Thumbnail": "",
      "Score": 109.0,
      "Tags": [
        "asset"
      ],
      "FileSize": 0,
      "LastModified": "",
      "IsSelectable": true,
      "Properties": {}
    },
    {
      "Id": "GlobalObjectId_V1-3-74633e2bc53bbb34fb92780a18551c77-28769715941901460-0",
      "Label": "",
      "Description": "",
      "Provider": "asset",
      "Type": "Asset",
      "Path": "Assets/SU3DJPFont/TextMeshProFont/Selected/mplus-2c-regular SDF.asset",
      "Thumbnail": "",
      "Score": 109.0,
      "Tags": [
        "asset"
      ],
      "FileSize": 0,
      "LastModified": "",
      "IsSelectable": true,
      "Properties": {}
    },
    {
      "Id": "GlobalObjectId_V1-3-759ea2e917ddbd748bbae914312e50db-5374006971853772513-0",
      "Label": "",
      "Description": "",
      "Provider": "asset",
      "Type": "Asset",
      "Path": "Assets/SU3DJPFont/TextMeshProFont/Dynamic/mplus-1c-regular SDF Dynamic.asset",
      "Thumbnail": "",
      "Score": 109.0,
      "Tags": [
        "asset"
      ],
      "FileSize": 0,
      "LastModified": "",
      "IsSelectable": true,
      "Properties": {}
    },
    {
      "Id": "GlobalObjectId_V1-3-7921be8cc10c03c478c87035ebcb76a6-11195867121905742015-0",
      "Label": "",
      "Description": "",
      "Provider": "asset",
      "Type": "Asset",
      "Path": "Assets/SU3DJPFont/TextMeshProFont/Dynamic/mplus-2m-light SDF Dynamic.asset",
      "Thumbnail": "",
      "Score": 109.0,
      "Tags": [
        "asset"
      ],
      "FileSize": 0,
      "LastModified": "",
      "IsSelectable": true,
      "Properties": {}
    },
    {
      "Id": "GlobalObjectId_V1-3-7ce76e80a4b85894a9e72d9ae402d529-8464943110496459697-0",
      "Label": "",
      "Description": "",
      "Provider": "asset",
      "Type": "Asset",
      "Path": "Assets/SU3DJPFont/TextMeshProFont/Dynamic/mplus-1m-regular SDF Dynamic.asset",
      "Thumbnail": "",
      "Score": 109.0,
      "Tags": [
        "asset"
      ],
      "FileSize": 0,
      "LastModified": "",
      "IsSelectable": true,
      "Properties": {}
    },
    {
      "Id": "GlobalObjectId_V1-3-812616e8e942d1d479e39467e245b4df-3472204388250812985-0",
      "Label": "",
      "Description": "",
      "Provider": "asset",
      "Type": "Asset",
      "Path": "Assets/SU3DJPFont/TextMeshProFont/Dynamic/mplus-2p-light SDF Dynamic.asset",
      "Thumbnail": "",
      "Score": 109.0,
      "Tags": [
        "asset"
      ],
      "FileSize": 0,
      "LastModified": "",
      "IsSelectable": true,
      "Properties": {}
    },
    {
      "Id": "GlobalObjectId_V1-3-85b2e958f4787f749a7f36c5730cad86-12377369105803955837-0",
      "Label": "",
      "Description": "",
      "Provider": "asset",
      "Type": "Asset",
      "Path": "Assets/SU3DJPFont/TextMeshProFont/Dynamic/mplus-1m-light SDF Dynamic.asset",
      "Thumbnail": "",
      "Score": 109.0,
      "Tags": [
        "asset"
      ],
      "FileSize": 0,
      "LastModified": "",
      "IsSelectable": true,
      "Properties": {}
    },
    {
      "Id": "GlobalObjectId_V1-3-86b13dc419f8c564aac0791dbc331bbb-12057675497592402659-0",
      "Label": "",
      "Description": "",
      "Provider": "asset",
      "Type": "Asset",
      "Path": "Assets/SU3DJPFont/TextMeshProFont/Dynamic/mplus-1mn-medium SDF Dynamic.asset",
      "Thumbnail": "",
      "Score": 109.0,
      "Tags": [
        "asset"
      ],
      "FileSize": 0,
      "LastModified": "",
      "IsSelectable": true,
      "Properties": {}
    },
    {
      "Id": "GlobalObjectId_V1-3-8b36acc553cf3014fb9e5610c3d60a2d-28337384096566610-0",
      "Label": "",
      "Description": "",
      "Provider": "asset",
      "Type": "Asset",
      "Path": "Assets/SU3DJPFont/TextMeshProFont/Selected/mplus-1c-medium SDF.asset",
      "Thumbnail": "",
      "Score": 109.0,
      "Tags": [
        "asset"
      ],
      "FileSize": 0,
      "LastModified": "",
      "IsSelectable": true,
      "Properties": {}
    },
    {
      "Id": "GlobalObjectId_V1-3-8f0c946662fabb047b4ff2f31c3e1139-8698229385396543811-0",
      "Label": "",
      "Description": "",
      "Provider": "asset",
      "Type": "Asset",
      "Path": "Assets/SU3DJPFont/TextMeshProFont/Dynamic/mplus-1p-black SDF Dynamic.asset",
      "Thumbnail": "",
      "Score": 109.0,
      "Tags": [
        "asset"
      ],
      "FileSize": 0,
      "LastModified": "",
      "IsSelectable": true,
      "Properties": {}
    },
    {
      "Id": "GlobalObjectId_V1-3-8f6c03dcf79094844b6d0e2e55c2b362-11919465196031250245-0",
      "Label": "",
      "Description": "",
      "Provider": "asset",
      "Type": "Asset",
      "Path": "Assets/SU3DJPFont/TextMeshProFont/Dynamic/mplus-2c-black SDF Dynamic.asset",
      "Thumbnail": "",
      "Score": 109.0,
      "Tags": [
        "asset"
      ],
      "FileSize": 0,
      "LastModified": "",
      "IsSelectable": true,
      "Properties": {}
    },
    {
      "Id": "GlobalObjectId_V1-3-8f8db4c6b8dc2844d931e4b0f1d3611c-28834229588162882-0",
      "Label": "",
      "Description": "",
      "Provider": "asset",
      "Type": "Asset",
      "Path": "Assets/SU3DJPFont/TextMeshProFont/Selected/mplus-2p-medium SDF.asset",
      "Thumbnail": "",
      "Score": 109.0,
      "Tags": [
        "asset"
      ],
      "FileSize": 0,
      "LastModified": "",
      "IsSelectable": true,
      "Properties": {}
    },
    {
      "Id": "GlobalObjectId_V1-3-90fa71e449dfb7445bed4a4df25a5989-28821477523766346-0",
      "Label": "",
      "Description": "",
      "Provider": "asset",
      "Type": "Asset",
      "Path": "Assets/SU3DJPFont/TextMeshProFont/Selected/mplus-2c-black SDF.asset",
      "Thumbnail": "",
      "Score": 109.0,
      "Tags": [
        "asset"
      ],
      "FileSize": 0,
      "LastModified": "",
      "IsSelectable": true,
      "Properties": {}
    },
    {
      "Id": "GlobalObjectId_V1-3-984bc697a12925f468a54076cca5a2c7-28258813395875818-0",
      "Label": "",
      "Description": "",
      "Provider": "asset",
      "Type": "Asset",
      "Path": "Assets/SU3DJPFont/TextMeshProFont/Selected/mplus-1m-regular SDF.asset",
      "Thumbnail": "",
      "Score": 109.0,
      "Tags": [
        "asset"
      ],
      "FileSize": 0,
      "LastModified": "",
      "IsSelectable": true,
      "Properties": {}
    },
    {
      "Id": "GlobalObjectId_V1-3-9b8566037841b8945aa878a021e60513-2554931652432421637-0",
      "Label": "",
      "Description": "",
      "Provider": "asset",
      "Type": "Asset",
      "Path": "Assets/SU3DJPFont/TextMeshProFont/Dynamic/mplus-2p-bold SDF Dynamic.asset",
      "Thumbnail": "",
      "Score": 109.0,
      "Tags": [
        "asset"
      ],
      "FileSize": 0,
      "LastModified": "",
      "IsSelectable": true,
      "Properties": {}
    },
    {
      "Id": "GlobalObjectId_V1-3-9d36de8f1d37e3f4b959c51720825d3a-28596847397631706-0",
      "Label": "",
      "Description": "",
      "Provider": "asset",
      "Type": "Asset",
      "Path": "Assets/SU3DJPFont/TextMeshProFont/Selected/mplus-1p-regular SDF.asset",
      "Thumbnail": "",
      "Score": 109.0,
      "Tags": [
        "asset"
      ],
      "FileSize": 0,
      "LastModified": "",
      "IsSelectable": true,
      "Properties": {}
    },
    {
      "Id": "GlobalObjectId_V1-3-9ed0bb7b96226c048a8d841f61b521d2-17452249466354332461-0",
      "Label": "",
      "Description": "",
      "Provider": "asset",
      "Type": "Asset",
      "Path": "Assets/SU3DJPFont/TextMeshProFont/Dynamic/mplus-1mn-thin SDF Dynamic.asset",
      "Thumbnail": "",
      "Score": 109.0,
      "Tags": [
        "asset"
      ],
      "FileSize": 0,
      "LastModified": "",
      "IsSelectable": true,
      "Properties": {}
    },
    {
      "Id": "GlobalObjectId_V1-3-a0e909b4601d95e4fb0464261cdac65e-28384433681461206-0",
      "Label": "",
      "Description": "",
      "Provider": "asset",
      "Type": "Asset",
      "Path": "Assets/SU3DJPFont/TextMeshProFont/Selected/mplus-2p-light SDF.asset",
      "Thumbnail": "",
      "Score": 109.0,
      "Tags": [
        "asset"
      ],
      "FileSize": 0,
      "LastModified": "",
      "IsSelectable": true,
      "Properties": {}
    },
    {
      "Id": "GlobalObjectId_V1-3-aaa7f84bf14d93a45806c37a16953942-5720201347372535957-0",
      "Label": "",
      "Description": "",
      "Provider": "asset",
      "Type": "Asset",
      "Path": "Assets/SU3DJPFont/TextMeshProFont/Dynamic/mplus-2p-black SDF Dynamic.asset",
      "Thumbnail": "",
      "Score": 109.0,
      "Tags": [
        "asset"
      ],
      "FileSize": 0,
      "LastModified": "",
      "IsSelectable": true,
      "Properties": {}
    },
    {
      "Id": "GlobalObjectId_V1-3-aaef09b2bc6f1ed4d95749b6629032da-28765259542651562-0",
      "Label": "",
      "Description": "",
      "Provider": "asset",
      "Type": "Asset",
      "Path": "Assets/SU3DJPFont/TextMeshProFont/Selected/mplus-1m-bold SDF.asset",
      "Thumbnail": "",
      "Score": 109.0,
      "Tags": [
        "asset"
      ],
      "FileSize": 0,
      "LastModified": "",
      "IsSelectable": true,
      "Properties": {}
    },
    {
      "Id": "GlobalObjectId_V1-3-ac1eddfdb36c2994eb798b47d9830b4a-8337301620631466263-0",
      "Label": "",
      "Description": "",
      "Provider": "asset",
      "Type": "Asset",
      "Path": "Assets/SU3DJPFont/TextMeshProFont/Dynamic/mplus-2m-regular SDF Dynamic.asset",
      "Thumbnail": "",
      "Score": 109.0,
      "Tags": [
        "asset"
      ],
      "FileSize": 0,
      "LastModified": "",
      "IsSelectable": true,
      "Properties": {}
    },
    {
      "Id": "GlobalObjectId_V1-3-bb779d5c1f115e44c82aa6f81b029f3f-14962274598633128021-0",
      "Label": "",
      "Description": "",
      "Provider": "asset",
      "Type": "Asset",
      "Path": "Assets/SU3DJPFont/TextMeshProFont/Dynamic/mplus-1c-black SDF Dynamic.asset",
      "Thumbnail": "",
      "Score": 109.0,
      "Tags": [
        "asset"
      ],
      "FileSize": 0,
      "LastModified": "",
      "IsSelectable": true,
      "Properties": {}
    },
    {
      "Id": "GlobalObjectId_V1-3-bbd8a03c4e0a6c74db2ea422d56165b5-28306986026175726-0",
      "Label": "",
      "Description": "",
      "Provider": "asset",
      "Type": "Asset",
      "Path": "Assets/SU3DJPFont/TextMeshProFont/Selected/mplus-2m-light SDF.asset",
      "Thumbnail": "",
      "Score": 109.0,
      "Tags": [
        "asset"
      ],
      "FileSize": 0,
      "LastModified": "",
      "IsSelectable": true,
      "Properties": {}
    },
    {
      "Id": "GlobalObjectId_V1-3-c105d02ccaa4a134090d1733b6cb419c-16374392809154110163-0",
      "Label": "",
      "Description": "",
      "Provider": "asset",
      "Type": "Asset",
      "Path": "Assets/SU3DJPFont/TextMeshProFont/Dynamic/mplus-2p-regular SDF Dynamic.asset",
      "Thumbnail": "",
      "Score": 109.0,
      "Tags": [
        "asset"
      ],
      "FileSize": 0,
      "LastModified": "",
      "IsSelectable": true,
      "Properties": {}
    },
    {
      "Id": "GlobalObjectId_V1-3-c1fe470c24d703a46af8b363646ea230-28371027054677040-0",
      "Label": "",
      "Description": "",
      "Provider": "asset",
      "Type": "Asset",
      "Path": "Assets/SU3DJPFont/TextMeshProFont/Selected/mplus-1p-heavy SDF.asset",
      "Thumbnail": "",
      "Score": 109.0,
      "Tags": [
        "asset"
      ],
      "FileSize": 0,
      "LastModified": "",
      "IsSelectable": true,
      "Properties": {}
    },
    {
      "Id": "GlobalObjectId_V1-3-c2312761d6138d34c97d2fccab8a3507-16891412772111732912-0",
      "Label": "",
      "Description": "",
      "Provider": "asset",
      "Type": "Asset",
      "Path": "Assets/SU3DJPFont/TextMeshProFont/Dynamic/mplus-1p-thin SDF Dynamic.asset",
      "Thumbnail": "",
      "Score": 109.0,
      "Tags": [
        "asset"
      ],
      "FileSize": 0,
      "LastModified": "",
      "IsSelectable": true,
      "Properties": {}
    },
    {
      "Id": "GlobalObjectId_V1-3-c2b6fe52bf6e9234184ddcaffd6bde96-28183392350554028-0",
      "Label": "",
      "Description": "",
      "Provider": "asset",
      "Type": "Asset",
      "Path": "Assets/SU3DJPFont/TextMeshProFont/Selected/mplus-2m-regular SDF.asset",
      "Thumbnail": "",
      "Score": 109.0,
      "Tags": [
        "asset"
      ],
      "FileSize": 0,
      "LastModified": "",
      "IsSelectable": true,
      "Properties": {}
    },
    {
      "Id": "GlobalObjectId_V1-3-c3868d1a5ce8cc143bd0ce2763d7b21c-4228579734095763063-0",
      "Label": "",
      "Description": "",
      "Provider": "asset",
      "Type": "Asset",
      "Path": "Assets/SU3DJPFont/TextMeshProFont/Dynamic/mplus-2c-regular SDF Dynamic.asset",
      "Thumbnail": "",
      "Score": 109.0,
      "Tags": [
        "asset"
      ],
      "FileSize": 0,
      "LastModified": "",
      "IsSelectable": true,
      "Properties": {}
    },
    {
      "Id": "GlobalObjectId_V1-3-c7a67346c4dd41441bfceb5719f825b0-9592684041878795124-0",
      "Label": "",
      "Description": "",
      "Provider": "asset",
      "Type": "Asset",
      "Path": "Assets/SU3DJPFont/TextMeshProFont/Dynamic/mplus-1p-heavy SDF Dynamic.asset",
      "Thumbnail": "",
      "Score": 109.0,
      "Tags": [
        "asset"
      ],
      "FileSize": 0,
      "LastModified": "",
      "IsSelectable": true,
      "Properties": {}
    },
    {
      "Id": "GlobalObjectId_V1-3-c8ccd8b044de8bd42b1aba46c0ddee8f-5998041609681348345-0",
      "Label": "",
      "Description": "",
      "Provider": "asset",
      "Type": "Asset",
      "Path": "Assets/SU3DJPFont/TextMeshProFont/Dynamic/mplus-1c-bold SDF Dynamic.asset",
      "Thumbnail": "",
      "Score": 109.0,
      "Tags": [
        "asset"
      ],
      "FileSize": 0,
      "LastModified": "",
      "IsSelectable": true,
      "Properties": {}
    },
    {
      "Id": "GlobalObjectId_V1-3-cc73e756710017048be3180191be6514-28765327644269866-0",
      "Label": "",
      "Description": "",
      "Provider": "asset",
      "Type": "Asset",
      "Path": "Assets/SU3DJPFont/TextMeshProFont/Selected/mplus-2c-light SDF.asset",
      "Thumbnail": "",
      "Score": 109.0,
      "Tags": [
        "asset"
      ],
      "FileSize": 0,
      "LastModified": "",
      "IsSelectable": true,
      "Properties": {}
    },
    {
      "Id": "GlobalObjectId_V1-3-cdd7b830eb46ebb42abfec333821465a-28534270554282302-0",
      "Label": "",
      "Description": "",
      "Provider": "asset",
      "Type": "Asset",
      "Path": "Assets/SU3DJPFont/TextMeshProFont/Selected/mplus-1c-bold SDF.asset",
      "Thumbnail": "",
      "Score": 109.0,
      "Tags": [
        "asset"
      ],
      "FileSize": 0,
      "LastModified": "",
      "IsSelectable": true,
      "Properties": {}
    },
    {
      "Id": "GlobalObjectId_V1-3-ce6cd73bef87e7c448c767a5aa75994d-28318190892293904-0",
      "Label": "",
      "Description": "",
      "Provider": "asset",
      "Type": "Asset",
      "Path": "Assets/SU3DJPFont/TextMeshProFont/Selected/mplus-2c-bold SDF.asset",
      "Thumbnail": "",
      "Score": 109.0,
      "Tags": [
        "asset"
      ],
      "FileSize": 0,
      "LastModified": "",
      "IsSelectable": true,
      "Properties": {}
    },
    {
      "Id": "GlobalObjectId_V1-3-cf759ee9428512f43bacb49e6caf5c2d-28396761704130438-0",
      "Label": "",
      "Description": "",
      "Provider": "asset",
      "Type": "Asset",
      "Path": "Assets/SU3DJPFont/TextMeshProFont/Selected/mplus-1mn-thin SDF.asset",
      "Thumbnail": "",
      "Score": 109.0,
      "Tags": [
        "asset"
      ],
      "FileSize": 0,
      "LastModified": "",
      "IsSelectable": true,
      "Properties": {}
    },
    {
      "Id": "GlobalObjectId_V1-3-d5163720ef195944ab97cfb3bd2158c9-7829374686260196578-0",
      "Label": "",
      "Description": "",
      "Provider": "asset",
      "Type": "Asset",
      "Path": "Assets/SU3DJPFont/TextMeshProFont/Dynamic/mplus-1m-thin SDF Dynamic.asset",
      "Thumbnail": "",
      "Score": 109.0,
      "Tags": [
        "asset"
      ],
      "FileSize": 0,
      "LastModified": "",
      "IsSelectable": true,
      "Properties": {}
    },
    {
      "Id": "GlobalObjectId_V1-3-d94daef05fa7cc34cb5c81214d5aea3e-8849012882736103158-0",
      "Label": "",
      "Description": "",
      "Provider": "asset",
      "Type": "Asset",
      "Path": "Assets/SU3DJPFont/TextMeshProFont/Dynamic/mplus-2c-heavy SDF Dynamic.asset",
      "Thumbnail": "",
      "Score": 109.0,
      "Tags": [
        "asset"
      ],
      "FileSize": 0,
      "LastModified": "",
      "IsSelectable": true,
      "Properties": {}
    },
    {
      "Id": "GlobalObjectId_V1-3-da6dd765a7de9fc4b9068a014571ed7e-28391300321799492-0",
      "Label": "",
      "Description": "",
      "Provider": "asset",
      "Type": "Asset",
      "Path": "Assets/SU3DJPFont/TextMeshProFont/Selected/mplus-1c-light SDF.asset",
      "Thumbnail": "",
      "Score": 109.0,
      "Tags": [
        "asset"
      ],
      "FileSize": 0,
      "LastModified": "",
      "IsSelectable": true,
      "Properties": {}
    },
    {
      "Id": "GlobalObjectId_V1-3-df6a9633926bea8458e6d31c7fe6a9e3-28323799494145198-0",
      "Label": "",
      "Description": "",
      "Provider": "asset",
      "Type": "Asset",
      "Path": "Assets/SU3DJPFont/TextMeshProFont/Selected/mplus-2m-medium SDF.asset",
      "Thumbnail": "",
      "Score": 109.0,
      "Tags": [
        "asset"
      ],
      "FileSize": 0,
      "LastModified": "",
      "IsSelectable": true,
      "Properties": {}
    },
    {
      "Id": "GlobalObjectId_V1-3-e2a3aedb5a5cd1d4d9993da0a70ac70f-7393330230452918123-0",
      "Label": "",
      "Description": "",
      "Provider": "asset",
      "Type": "Asset",
      "Path": "Assets/SU3DJPFont/TextMeshProFont/Dynamic/mplus-2c-thin SDF Dynamic.asset",
      "Thumbnail": "",
      "Score": 109.0,
      "Tags": [
        "asset"
      ],
      "FileSize": 0,
      "LastModified": "",
      "IsSelectable": true,
      "Properties": {}
    },
    {
      "Id": "GlobalObjectId_V1-3-ea2e161aed484864886ae060b3828dab-12072290636675512618-0",
      "Label": "",
      "Description": "",
      "Provider": "asset",
      "Type": "Asset",
      "Path": "Assets/SU3DJPFont/TextMeshProFont/Dynamic/mplus-2c-medium SDF Dynamic.asset",
      "Thumbnail": "",
      "Score": 109.0,
      "Tags": [
        "asset"
      ],
      "FileSize": 0,
      "LastModified": "",
      "IsSelectable": true,
      "Properties": {}
    },
    {
      "Id": "GlobalObjectId_V1-3-ed9accc231f96b141b88b6108567d563-7109968224897591074-0",
      "Label": "",
      "Description": "",
      "Provider": "asset",
      "Type": "Asset",
      "Path": "Assets/SU3DJPFont/TextMeshProFont/Dynamic/mplus-1c-heavy SDF Dynamic.asset",
      "Thumbnail": "",
      "Score": 109.0,
      "Tags": [
        "asset"
      ],
      "FileSize": 0,
      "LastModified": "",
      "IsSelectable": true,
      "Properties": {}
    },
    {
      "Id": "GlobalObjectId_V1-3-f10d6a9661f63094e97279668785d4f9-28581170383494170-0",
      "Label": "",
      "Description": "",
      "Provider": "asset",
      "Type": "Asset",
      "Path": "Assets/SU3DJPFont/TextMeshProFont/Selected/mplus-1mn-regular SDF.asset",
      "Thumbnail": "",
      "Score": 109.0,
      "Tags": [
        "asset"
      ],
      "FileSize": 0,
      "LastModified": "",
      "IsSelectable": true,
      "Properties": {}
    },
    {
      "Id": "GlobalObjectId_V1-3-f83479b3119682b4381726927e81ce85-11355717162410324380-0",
      "Label": "",
      "Description": "",
      "Provider": "asset",
      "Type": "Asset",
      "Path": "Assets/SU3DJPFont/TextMeshProFont/Dynamic/mplus-2m-bold SDF Dynamic.asset",
      "Thumbnail": "",
      "Score": 109.0,
      "Tags": [
        "asset"
      ],
      "FileSize": 0,
      "LastModified": "",
      "IsSelectable": true,
      "Properties": {}
    },
    {
      "Id": "GlobalObjectId_V1-3-f86c285d89a38b3419da63ff6d5f1319-6108000441910707921-0",
      "Label": "",
      "Description": "",
      "Provider": "asset",
      "Type": "Asset",
      "Path": "Assets/SU3DJPFont/TextMeshProFont/Dynamic/mplus-2c-bold SDF Dynamic.asset",
      "Thumbnail": "",
      "Score": 109.0,
      "Tags": [
        "asset"
      ],
      "FileSize": 0,
      "LastModified": "",
      "IsSelectable": true,
      "Properties": {}
    },
    {
      "Id": "GlobalObjectId_V1-3-f9215b90cd5de96469c85530662b8c2d-28629500682034880-0",
      "Label": "",
      "Description": "",
      "Provider": "asset",
      "Type": "Asset",
      "Path": "Assets/SU3DJPFont/TextMeshProFont/Selected/mplus-2p-black SDF.asset",
      "Thumbnail": "",
      "Score": 109.0,
      "Tags": [
        "asset"
      ],
      "FileSize": 0,
      "LastModified": "",
      "IsSelectable": true,
      "Properties": {}
    },
    {
      "Id": "GlobalObjectId_V1-3-fcd455ab112b0a842a2b67aa57afd741-28900705097119640-0",
      "Label": "",
      "Description": "",
      "Provider": "asset",
      "Type": "Asset",
      "Path": "Assets/SU3DJPFont/TextMeshProFont/Selected/mplus-1mn-light SDF.asset",
      "Thumbnail": "",
      "Score": 109.0,
      "Tags": [
        "asset"
      ],
      "FileSize": 0,
      "LastModified": "",
      "IsSelectable": true,
      "Properties": {}
    },
    {
      "Id": "GlobalObjectId_V1-3-fd903416ccaef7c44a3cf18eb9e1ab60-28008007510019082-0",
      "Label": "",
      "Description": "",
      "Provider": "asset",
      "Type": "Asset",
      "Path": "Assets/SU3DJPFont/TextMeshProFont/Selected/mplus-2p-bold SDF.asset",
      "Thumbnail": "",
      "Score": 109.0,
      "Tags": [
        "asset"
      ],
      "FileSize": 0,
      "LastModified": "",
      "IsSelectable": true,
      "Properties": {}
    },
    {
      "Id": "GlobalObjectId_V1-3-fefe5870091d25a4b9dfd6f28eebeee9-12535343705822383314-0",
      "Label": "",
      "Description": "",
      "Provider": "asset",
      "Type": "Asset",
      "Path": "Assets/SU3DJPFont/TextMeshProFont/Dynamic/mplus-1p-regular SDF Dynamic.asset",
      "Thumbnail": "",
      "Score": 109.0,
      "Tags": [
        "asset"
      ],
      "FileSize": 0,
      "LastModified": "",
      "IsSelectable": true,
      "Properties": {}
    },
    {
      "Id": "GlobalObjectId_V1-1-ee8be02e261755e4883215de2e113e0d-2800000-0",
      "Label": "",
      "Description": "",
      "Provider": "asset",
      "Type": "Asset",
      "Path": "Assets/Particlecollection_Free samples/Texture/power_03.png",
      "Thumbnail": "",
      "Score": 112.0,
      "Tags": [
        "asset"
      ],
      "FileSize": 0,
      "LastModified": "",
      "IsSelectable": true,
      "Properties": {}
    },
    {
      "Id": "GlobalObjectId_V1-1-fa0c7416c0e0db341853a137b5c6bcd6-2800000-0",
      "Label": "",
      "Description": "",
      "Provider": "asset",
      "Type": "Asset",
      "Path": "Assets/Particlecollection_Free samples/Texture/power_01.png",
      "Thumbnail": "",
      "Score": 112.0,
      "Tags": [
        "asset"
      ],
      "FileSize": 0,
      "LastModified": "",
      "IsSelectable": true,
      "Properties": {}
    },
    {
      "Id": "GlobalObjectId_V1-1-1a2e6115c02ae054a817d4238e18e36c-2800000-0",
      "Label": "",
      "Description": "",
      "Provider": "asset",
      "Type": "Asset",
      "Path": "Assets/texture/qwantani_afternoon_puresky_4k.exr",
      "Thumbnail": "",
      "Score": 113.0,
      "Tags": [
        "asset"
      ],
      "FileSize": 0,
      "LastModified": "",
      "IsSelectable": true,
      "Properties": {}
    },
    {
      "Id": "GlobalObjectId_V1-1-0380d71e6f704f64a85ddb30cd95595f-2800000-0",
      "Label": "",
      "Description": "",
      "Provider": "asset",
      "Type": "Asset",
      "Path": "Assets/Particlecollection_Free samples/Texture/rock_04.png",
      "Thumbnail": "",
      "Score": 114.0,
      "Tags": [
        "asset"
      ],
      "FileSize": 0,
      "LastModified": "",
      "IsSelectable": true,
      "Properties": {}
    },
    {
      "Id": "GlobalObjectId_V1-1-353708b27c4e0bf4b90186ea79227ece-2800000-0",
      "Label": "",
      "Description": "",
      "Provider": "asset",
      "Type": "Asset",
      "Path": "Assets/Particlecollection_Free samples/Texture/star_02.png",
      "Thumbnail": "",
      "Score": 115.0,
      "Tags": [
        "asset"
      ],
      "FileSize": 0,
      "LastModified": "",
      "IsSelectable": true,
      "Properties": {}
    },
    {
      "Id": "GlobalObjectId_V1-1-72b005d0d3b47254c8f8bf8899a6510f-2800000-0",
      "Label": "",
      "Description": "",
      "Provider": "asset",
      "Type": "Asset",
      "Path": "Assets/Particlecollection_Free samples/Texture/smoke_06.png",
      "Thumbnail": "",
      "Score": 115.0,
      "Tags": [
        "asset"
      ],
      "FileSize": 0,
      "LastModified": "",
      "IsSelectable": true,
      "Properties": {}
    },
    {
      "Id": "GlobalObjectId_V1-1-e4288234861fa2e4fbc6a0fbec1269dd-2800000-0",
      "Label": "",
      "Description": "",
      "Provider": "asset",
      "Type": "Asset",
      "Path": "Assets/Particlecollection_Free samples/Texture/star_01.png",
      "Thumbnail": "",
      "Score": 115.0,
      "Tags": [
        "asset"
      ],
      "FileSize": 0,
      "LastModified": "",
      "IsSelectable": true,
      "Properties": {}
    },
    {
      "Id": "GlobalObjectId_V1-1-fe095ce6b171a6547ad96df5989c2ad7-2800000-0",
      "Label": "",
      "Description": "",
      "Provider": "asset",
      "Type": "Asset",
      "Path": "Assets/Particlecollection_Free samples/Texture/starbox.png",
      "Thumbnail": "",
      "Score": 115.0,
      "Tags": [
        "asset"
      ],
      "FileSize": 0,
      "LastModified": "",
      "IsSelectable": true,
      "Properties": {}
    },
    {
      "Id": "GlobalObjectId_V1-1-06ccbbe2a953ec94fb0d25091e9df7db-2800000-0",
      "Label": "",
      "Description": "",
      "Provider": "asset",
      "Type": "Asset",
      "Path": "Assets/Model/TextureHorro/texture_pbr_20250901_normal.001.png",
      "Thumbnail": "",
      "Score": 116.0,
      "Tags": [
        "asset"
      ],
      "FileSize": 0,
      "LastModified": "",
      "IsSelectable": true,
      "Properties": {}
    },
    {
      "Id": "GlobalObjectId_V1-1-1331a41e4a8bda34abfe0f725d0808c2-2800000-0",
      "Label": "",
      "Description": "",
      "Provider": "asset",
      "Type": "Asset",
      "Path": "Assets/Model/TextureHorro/texture_pbr_20250901_metallic-texture_pbr_20250901_roughness.png",
      "Thumbnail": "",
      "Score": 116.0,
      "Tags": [
        "asset"
      ],
      "FileSize": 0,
      "LastModified": "",
      "IsSelectable": true,
      "Properties": {}
    },
    {
      "Id": "GlobalObjectId_V1-1-280d25bd8d97c87498eba7abcb7153e4-2800000-0",
      "Label": "",
      "Description": "",
      "Provider": "asset",
      "Type": "Asset",
      "Path": "Assets/Model/TextureHorro/texture_pbr_20250901.png",
      "Thumbnail": "",
      "Score": 116.0,
      "Tags": [
        "asset"
      ],
      "FileSize": 0,
      "LastModified": "",
      "IsSelectable": true,
      "Properties": {}
    },
    {
      "Id": "GlobalObjectId_V1-1-396d8a85045e1844a8e447fa0be821dc-2800000-0",
      "Label": "",
      "Description": "",
      "Provider": "asset",
      "Type": "Asset",
      "Path": "Assets/Model/TextureHorro/texture_pbr_20250901_metallic-texture_pbr_20250901_roughnes.png",
      "Thumbnail": "",
      "Score": 116.0,
      "Tags": [
        "asset"
      ],
      "FileSize": 0,
      "LastModified": "",
      "IsSelectable": true,
      "Properties": {}
    },
    {
      "Id": "GlobalObjectId_V1-1-3c9ab0bfdf97c164f8fc5a4891ea4762-2800000-0",
      "Label": "",
      "Description": "",
      "Provider": "asset",
      "Type": "Asset",
      "Path": "Assets/texture/texture_pbr_20250901.png",
      "Thumbnail": "",
      "Score": 116.0,
      "Tags": [
        "asset"
      ],
      "FileSize": 0,
      "LastModified": "",
      "IsSelectable": true,
      "Properties": {}
    },
    {
      "Id": "GlobalObjectId_V1-1-4ad432aabf3dc1946ba781f7746fee8a-2800000-0",
      "Label": "",
      "Description": "",
      "Provider": "asset",
      "Type": "Asset",
      "Path": "Assets/Model/zakoTexture/texture_pbr_20250901_normal.002.png",
      "Thumbnail": "",
      "Score": 116.0,
      "Tags": [
        "asset"
      ],
      "FileSize": 0,
      "LastModified": "",
      "IsSelectable": true,
      "Properties": {}
    },
    {
      "Id": "GlobalObjectId_V1-1-4f8ada9dcd5bb4543bdcf23cc02d1f68-2800000-0",
      "Label": "",
      "Description": "",
      "Provider": "asset",
      "Type": "Asset",
      "Path": "Assets/Model/zakoTexture/texture_pbr_20250901_metallic-texture_pbr_20250901_roughnes.001.png",
      "Thumbnail": "",
      "Score": 116.0,
      "Tags": [
        "asset"
      ],
      "FileSize": 0,
      "LastModified": "",
      "IsSelectable": true,
      "Properties": {}
    },
    {
      "Id": "GlobalObjectId_V1-1-71273d14e3fef9d47b725a1cee48ab75-2800000-0",
      "Label": "",
      "Description": "",
      "Provider": "asset",
      "Type": "Asset",
      "Path": "Assets/Model/textureChuboss/texture_pbr_20250901_metallic-texture_pbr_20250901_roughnes.png",
      "Thumbnail": "",
      "Score": 116.0,
      "Tags": [
        "asset"
      ],
      "FileSize": 0,
      "LastModified": "",
      "IsSelectable": true,
      "Properties": {}
    },
    {
      "Id": "GlobalObjectId_V1-1-84f9127668ea07046aea404efda833af-2800000-0",
      "Label": "",
      "Description": "",
      "Provider": "asset",
      "Type": "Asset",
      "Path": "Assets/Model/textureChuboss/texture_pbr_20250901_normal.001.png",
      "Thumbnail": "",
      "Score": 116.0,
      "Tags": [
        "asset"
      ],
      "FileSize": 0,
      "LastModified": "",
      "IsSelectable": true,
      "Properties": {}
    },
    {
      "Id": "GlobalObjectId_V1-1-91c88f5699bc13d479da0c9390ef1410-2800000-0",
      "Label": "",
      "Description": "",
      "Provider": "asset",
      "Type": "Asset",
      "Path": "Assets/Model/TextureHorro/texture_pbr_20250901_normal.png",
      "Thumbnail": "",
      "Score": 116.0,
      "Tags": [
        "asset"
      ],
      "FileSize": 0,
      "LastModified": "",
      "IsSelectable": true,
      "Properties": {}
    },
    {
      "Id": "GlobalObjectId_V1-1-9f0512d4694b01f4fbdbada148692044-2800000-0",
      "Label": "",
      "Description": "",
      "Provider": "asset",
      "Type": "Asset",
      "Path": "Assets/Model/TextureHorro/texture_pbr_20250901.001.png",
      "Thumbnail": "",
      "Score": 116.0,
      "Tags": [
        "asset"
      ],
      "FileSize": 0,
      "LastModified": "",
      "IsSelectable": true,
      "Properties": {}
    },
    {
      "Id": "GlobalObjectId_V1-1-c1bd9cd96cb9f104d858e7d8b1f855b5-2800000-0",
      "Label": "",
      "Description": "",
      "Provider": "asset",
      "Type": "Asset",
      "Path": "Assets/Model/zakoTexture/texture_pbr_20250901.002.png",
      "Thumbnail": "",
      "Score": 116.0,
      "Tags": [
        "asset"
      ],
      "FileSize": 0,
      "LastModified": "",
      "IsSelectable": true,
      "Properties": {}
    },
    {
      "Id": "GlobalObjectId_V1-1-f0a3b30d4f2ff4743a6b410e9ad71231-2800000-0",
      "Label": "",
      "Description": "",
      "Provider": "asset",
      "Type": "Asset",
      "Path": "Assets/Model/textureChuboss/texture_pbr_20250901.001.png",
      "Thumbnail": "",
      "Score": 116.0,
      "Tags": [
        "asset"
      ],
      "FileSize": 0,
      "LastModified": "",
      "IsSelectable": true,
      "Properties": {}
    },
    {
      "Id": "GlobalObjectId_V1-1-fcbc2e23daee107458e174cb6ab4257b-2800000-0",
      "Label": "",
      "Description": "",
      "Provider": "asset",
      "Type": "Asset",
      "Path": "Assets/Particlecollection_Free samples/Texture/toon_01.png",
      "Thumbnail": "",
      "Score": 116.0,
      "Tags": [
        "asset"
      ],
      "FileSize": 0,
      "LastModified": "",
      "IsSelectable": true,
      "Properties": {}
    },
    {
      "Id": "GlobalObjectId_V1-1-0cd14b03693f0834194f25152cbc6b8d-2800000-0",
      "Label": "",
      "Description": "",
      "Provider": "asset",
      "Type": "Asset",
      "Path": "Assets/Model/uploads_files_1894371_lp_01+-+Default_BaseColor.tga",
      "Thumbnail": "",
      "Score": 117.0,
      "Tags": [
        "asset"
      ],
      "FileSize": 0,
      "LastModified": "",
      "IsSelectable": true,
      "Properties": {}
    },
    {
      "Id": "GlobalObjectId_V1-1-b531a4ebbb9d5a548b0c23fcc60ef88f-2800000-0",
      "Label": "",
      "Description": "",
      "Provider": "asset",
      "Type": "Asset",
      "Path": "Assets/Model/uploads_files_1965324_lp_grey_BaseColor.tga",
      "Thumbnail": "",
      "Score": 117.0,
      "Tags": [
        "asset"
      ],
      "FileSize": 0,
      "LastModified": "",
      "IsSelectable": true,
      "Properties": {}
    }
  ]
}